<?xml version="1.0" ?><graphml xmlns="http://graphml.graphdrawing.org/xmlns" xmlns:xsi="http://www.w3.org/2001/XMLSchema-instance" xsi:schemaLocation="http://graphml.graphdrawing.org/xmlns http://graphml.graphdrawing.org/xmlns/1.1/graphml.xsd"><key id="mechanism" for="node" attr.name="mechanism" attr.type="string"></key><graph id="G" edgedefault="directed"><node id="n1140"><data key="mechanism">mechanism-d4-b0-d3-b1</data></node><node id="n299"><data key="mechanism">mechanism-d4-b0-d3-b1-d2-b0-d1-b0</data></node><node id="n758"><data key="mechanism">mechanism-d4-b0-d3-b1-d2-b0-d1-b0-d0-b0</data></node><node id="n756"><data key="mechanism">mechanism-d4-b0-d3-b1</data></node><node id="n298"><data key="mechanism">mechanism-d4-b0-d3-b1-d2-b0-d1-b0-d0-b0</data></node><node id="n552"><data key="mechanism">mechanism-d4-b0-d3-b1</data></node><node id="n886"><data key="mechanism">mechanism-d4-b0-d3-b1-d2-b0-d1-b0-d0-b0</data></node><node id="n754"><data key="mechanism">mechanism-d4-b0-d3-b1-d2-b0-d1-b0</data></node><node id="n884"><data key="mechanism">mechanism-d4-b0-d3-b1-d2-b0-d1-b0-d0-b0</data></node><node id="n613"><data key="mechanism">mechanism-d4-b0-d3-b1-d2-b0</data></node><node id="n818"><data key="mechanism">mechanism-d4-b0-d3-b1-d2-b0</data></node><node id="n559"><data key="mechanism">mechanism-d4-b0-d3-b1-d2-b0-d1-b0</data></node><node id="n411"><data key="mechanism">mechanism-d4-b0-d3-b1-d2-b0-d1-b0</data></node><node id="n750"><data key="mechanism">mechanism-d4-b0-d3-b1-d2-b0-d1-b0</data></node><node id="n618"><data key="mechanism">mechanism-d4-b0-d3-b1-d2-b0-d1-b0-d0-b0</data></node><node id="n687"><data key="mechanism">mechanism-d4-b0-d3-b1-d2-b0-d1-b0</data></node><node id="n951"><data key="mechanism">mechanism-d4-b0-d3-b1</data></node><node id="n213"><data key="mechanism">mechanism-d4-b0-d3-b1-d2-b0-d1-b0-d0-b0</data></node><node id="n619"><data key="mechanism">mechanism-d4-b0-d3-b1-d2-b0-d1-b0-d0-b0</data></node><node id="n813"><data key="mechanism">mechanism-d4-b0-d3-b1-d2-b0</data></node><node id="n210"><data key="mechanism">mechanism-d4-b0-d3-b1-d2-b0-d1-b0</data></node><node id="n1147"><data key="mechanism">mechanism-d4-b0-d3-b1-d2-b0-d1-b0</data></node><node id="n353"><data key="mechanism">mechanism-d4-b0-d3-b1-d2-b0-d1-b0-d0-b0</data></node><node id="n496"><data key="mechanism">mechanism-d4-b0-d3-b1-d2-b0</data></node><node id="n409"><data key="mechanism">mechanism-d4-b0-d3-b1-d2-b0</data></node><node id="n407"><data key="mechanism">mechanism-d4-b0-d3-b1-d2-b0-d1-b0</data></node><node id="n749"><data key="mechanism">mechanism-d4-b0-d3-b1-d2-b0-d1-b0</data></node><node id="n406"><data key="mechanism">mechanism-d4-b0-d3-b1-d2-b0</data></node><node id="n405"><data key="mechanism">mechanism-d4-b0-d3-b1-d2-b0-d1-b0-d0-b0</data></node><node id="n898"><data key="mechanism">mechanism-d4-b0-d3-b1-d2-b0-d1-b0</data></node><node id="n404"><data key="mechanism">mechanism-d4-b0-d3-b1</data></node><node id="n545"><data key="mechanism">mechanism-d4-b0-d3-b1-d2-b0-d1-b0-d0-b0</data></node><node id="n602"><data key="mechanism">mechanism-d4-b0-d3-b1-d2-b0-d1-b0-d0-b0</data></node><node id="n698"><data key="mechanism">mechanism-d4-b0-d3-b1-d2-b0-d1-b0-d0-b0</data></node><node id="n804"><data key="mechanism">mechanism-d4-b0-d3-b1-d2-b0-d1-b0</data></node><node id="n693"><data key="mechanism">mechanism-d4-b0-d3-b1-d2-b0-d1-b0</data></node><node id="n292"><data key="mechanism">mechanism-d4-b0-d3-b1-d2-b0-d1-b0-d0-b0</data></node><node id="n489"><data key="mechanism">mechanism-d4-b0-d3-b1</data></node><node id="n176"><data key="mechanism">mechanism-d4-b0-d3-b1-d2-b0-d1-b0-d0-b0</data></node><node id="n178"><data key="mechanism">mechanism-d4-b0-d3-b1-d2-b0</data></node><node id="n944"><data key="mechanism">mechanism-d4-b0-d3-b1-d2-b0-d1-b0-d0-b0</data></node><node id="n533"><data key="mechanism">mechanism-d4-b0-d3-b1</data></node><node id="n532"><data key="mechanism">mechanism-d4-b0-d3-b1-d2-b0-d1-b0</data></node><node id="n738"><data key="mechanism">mechanism-d4-b0-d3-b1-d2-b0-d1-b0-d0-b0</data></node><node id="n538"><data key="mechanism">mechanism-d4-b0-d3-b1-d2-b0-d1-b0</data></node><node id="n1020"><data key="mechanism">mechanism-d4-b0-d3-b1-d2-b0-d1-b0</data></node><node id="n731"><data key="mechanism">mechanism-d4-b0-d3-b1-d2-b0-d1-b0-d0-b0</data></node><node id="n636"><data key="mechanism">mechanism-d4-b0-d3-b1-d2-b0-d1-b0-d0-b0</data></node><node id="n434"><data key="mechanism">mechanism-d4-b0-d3-b1-d2-b0-d1-b0-d0-b0</data></node><node id="n1025"><data key="mechanism">mechanism-d4-b0-d3-b1-d2-b0</data></node><node id="n232"><data key="mechanism">mechanism-d4-b0-d3-b1-d2-b0-d1-b0-d0-b0</data></node><node id="n836"><data key="mechanism">mechanism-d4-b0-d3-b1-d2-b0-d1-b0-d0-b0</data></node><node id="n339"><data key="mechanism">mechanism-d4-b0-d3-b1-d2-b0-d1-b0-d0-b0</data></node><node id="n238"><data key="mechanism">mechanism-d4-b0-d3-b1-d2-b0</data></node><node id="n830"><data key="mechanism">mechanism-d4-b0-d3-b1-d2-b0-d1-b0-d0-b0</data></node><node id="n333"><data key="mechanism">mechanism-d4-b0-d3-b1-d2-b0</data></node><node id="n239"><data key="mechanism">mechanism-d4-b0-d3-b1-d2-b0</data></node><node id="n722"><data key="mechanism">mechanism-d4-b0-d3-b1-d2-b0-d1-b0-d0-b0</data></node><node id="n426"><data key="mechanism">mechanism-d4-b0-d3-b1-d2-b0-d1-b0</data></node><node id="n724"><data key="mechanism">mechanism-d4-b0-d3-b1-d2-b0-d1-b0-d0-b0</data></node><node id="n728"><data key="mechanism">mechanism-d4-b0-d3-b1-d2-b0-d1-b0-d0-b0</data></node><node id="n429"><data key="mechanism">mechanism-d4-b0-d3-b1-d2-b0-d1-b0-d0-b0</data></node><node id="n720"><data key="mechanism">mechanism-d4-b0-d3-b1-d2-b0</data></node><node id="n221"><data key="mechanism">mechanism-d4-b0-d3-b1-d2-b0-d1-b0-d0-b0</data></node><node id="n826"><data key="mechanism">mechanism-d4-b0-d3-b1-d2-b0-d1-b0-d0-b0</data></node><node id="n820"><data key="mechanism">mechanism-d4-b0-d3-b1-d2-b0-d1-b0</data></node><node id="n822"><data key="mechanism">mechanism-d4-b0-d3-b1-d2-b0-d1-b0-d0-b0</data></node><node id="n326"><data key="mechanism">mechanism-d4-b0-d3-b1-d2-b0-d1-b0-d0-b0</data></node><node id="n823"><data key="mechanism">mechanism-d4-b0-d3-b1-d2-b0-d1-b0-d0-b0</data></node><node id="n921"><data key="mechanism">mechanism-d4-b0-d3-b1-d2-b0-d1-b0</data></node><node id="n197"><data key="mechanism">mechanism-d4-b0-d3-b1-d2-b0-d1-b0-d0-b0</data></node><node id="n199"><data key="mechanism">mechanism-d4-b0-d3-b1-d2-b0</data></node><node id="n913"><data key="mechanism">mechanism-d4-b0-d3-b1-d2-b0-d1-b0-d0-b0</data></node><node id="n1087"><data key="mechanism">mechanism-d4-b0-d3-b1-d2-b0-d1-b0</data></node><node id="n1118"><data key="mechanism">mechanism-d4-b0-d3-b1</data></node><node id="n396"><data key="mechanism">mechanism-d4-b0-d3-b1-d2-b0</data></node><node id="n915"><data key="mechanism">mechanism-d4-b0-d3-b1-d2-b0-d1-b0-d0-b0</data></node><node id="n394"><data key="mechanism">mechanism-d4-b0-d3-b1-d2-b0-d1-b0</data></node><node id="n1086"><data key="mechanism">mechanism-d4-b0-d3-b1-d2-b0-d1-b0-d0-b0</data></node><node id="n258"><data key="mechanism">mechanism-d4-b0-d3-b1-d2-b0-d1-b0-d0-b0</data></node><node id="n714"><data key="mechanism">mechanism-d4-b0-d3-b1-d2-b0</data></node><node id="n715"><data key="mechanism">mechanism-d4-b0-d3-b1-d2-b0-d1-b0-d0-b0</data></node><node id="n599"><data key="mechanism">mechanism-d4-b0-d3-b1-d2-b0-d1-b0-d0-b0</data></node><node id="n505"><data key="mechanism">mechanism-d4-b0-d3-b1-d2-b0-d1-b0-d0-b0</data></node><node id="n648"><data key="mechanism">mechanism-d4-b0-d3-b1-d2-b0-d1-b0</data></node><node id="n507"><data key="mechanism">mechanism-d4-b0-d3-b1-d2-b0-d1-b0-d0-b0</data></node><node id="n785"><data key="mechanism">mechanism-d4-b0-d3-b1-d2-b0-d1-b0-d0-b0</data></node><node id="n1011"><data key="mechanism">mechanism-d4-b0-d3-b1-d2-b0-d1-b0-d0-b0</data></node><node id="n851"><data key="mechanism">mechanism-d4-b0-d3-b1-d2-b0-d1-b0-d0-b0</data></node><node id="n850"><data key="mechanism">mechanism-d4-b0-d3-b1-d2-b0-d1-b0-d0-b0</data></node><node id="n719"><data key="mechanism">mechanism-d4-b0-d3-b1-d2-b0</data></node><node id="n1013"><data key="mechanism">mechanism-d4-b0-d3-b1-d2-b0-d1-b0-d0-b0</data></node><node id="n997"><data key="mechanism">mechanism-d4-b0-d3-b1-d2-b0-d1-b0-d0-b0</data></node><node id="n996"><data key="mechanism">mechanism-d4-b0-d3-b1-d2-b0</data></node><node id="n643"><data key="mechanism">mechanism-d4-b0-d3-b1-d2-b0-d1-b0-d0-b0</data></node><node id="n640"><data key="mechanism">mechanism-d4-b0-d3-b1-d2-b0-d1-b0</data></node><node id="n859"><data key="mechanism">mechanism-d4-b0-d3-b1-d2-b0-d1-b0-d0-b0</data></node><node id="n919"><data key="mechanism">mechanism-d4-b0-d3-b1-d2-b0-d1-b0-d0-b0</data></node><node id="n1108"><data key="mechanism">mechanism-d4-b0-d3-b1-d2-b0-d1-b0-d0-b0</data></node><node id="n904"><data key="mechanism">mechanism-d4-b0-d3-b1-d2-b0-d1-b0-d0-b0</data></node><node id="n445"><data key="mechanism">mechanism-d4-b0-d3-b1</data></node><node id="n1098"><data key="mechanism">mechanism-d4-b0-d3-b1-d2-b0-d1-b0-d0-b0</data></node><node id="n249"><data key="mechanism">mechanism-d4-b0-d3-b1-d2-b0</data></node><node id="n1096"><data key="mechanism">mechanism-d4-b0-d3-b1-d2-b0-d1-b0-d0-b0</data></node><node id="n1103"><data key="mechanism">mechanism-d4-b0-d3-b1-d2-b0-d1-b0-d0-b0</data></node><node id="n1093"><data key="mechanism">mechanism-d4-b0-d3-b1</data></node><node id="n246"><data key="mechanism">mechanism-d4-b0-d3-b1-d2-b0-d1-b0</data></node><node id="n241"><data key="mechanism">mechanism-d4-b0-d3-b1-d2-b0-d1-b0-d0-b0</data></node><node id="n587"><data key="mechanism">mechanism-d4-b0-d3-b1-d2-b0-d1-b0</data></node><node id="n240"><data key="mechanism">mechanism-d4-b0-d3-b1-d2-b0-d1-b0-d0-b0</data></node><node id="n446"><data key="mechanism">mechanism-d4-b0-d3-b1-d2-b0-d1-b0-d0-b0</data></node><node id="n518"><data key="mechanism">mechanism-d4-b0-d3-b1-d2-b0-d1-b0-d0-b0</data></node><node id="n792"><data key="mechanism">mechanism-d4-b0-d3-b1-d2-b0-d1-b0-d0-b0</data></node><node id="n517"><data key="mechanism">mechanism-d4-b0-d3-b1-d2-b0-d1-b0-d0-b0</data></node><node id="n514"><data key="mechanism">mechanism-d4-b0-d3-b1-d2-b0-d1-b0-d0-b0</data></node><node id="n794"><data key="mechanism">mechanism-d4-b0-d3-b1</data></node><node id="n1001"><data key="mechanism">mechanism-d4-b0-d3-b1-d2-b0-d1-b0-d0-b0</data></node><node id="n795"><data key="mechanism">mechanism-d4-b0-d3-b1-d2-b0-d1-b0-d0-b0</data></node><node id="n512"><data key="mechanism">mechanism-d4-b0-d3-b1-d2-b0-d1-b0-d0-b0</data></node><node id="n709"><data key="mechanism">mechanism-d4-b0-d3-b1-d2-b0</data></node><node id="n513"><data key="mechanism">mechanism-d4-b0-d3-b1-d2-b0-d1-b0</data></node><node id="n843"><data key="mechanism">mechanism-d4-b0-d3-b1-d2-b0</data></node><node id="n1101"><data key="mechanism">mechanism-d4-b0-d3-b1-d2-b0-d1-b0</data></node><node id="n909"><data key="mechanism">mechanism-d4-b0-d3-b1-d2-b0</data></node><node id="n984"><data key="mechanism">mechanism-d4-b0-d3-b1-d2-b0-d1-b0-d0-b0</data></node><node id="n983"><data key="mechanism">mechanism-d4-b0-d3-b1-d2-b0-d1-b0</data></node><node id="n390"><data key="mechanism">mechanism-d4-b0-d3-b1-d2-b0-d1-b0-d0-b0</data></node><node id="n908"><data key="mechanism">mechanism-d4-b0-d3-b1-d2-b0-d1-b0-d0-b0</data></node><node id="n905"><data key="mechanism">mechanism-d4-b0-d3-b1-d2-b0-d1-b0-d0-b0</data></node><node id="n849"><data key="mechanism">mechanism-d4-b0-d3-b1-d2-b0</data></node><node id="n848"><data key="mechanism">mechanism-d4-b0-d3-b1-d2-b0-d1-b0</data></node><node id="n1062"><data key="mechanism">mechanism-d4-b0-d3-b1-d2-b0-d1-b0-d0-b0</data></node><node id="n1137"><data key="mechanism">mechanism-d4-b0-d3-b1-d2-b0-d1-b0-d0-b0</data></node><node id="n377"><data key="mechanism">mechanism-d4-b0-d3-b1</data></node><node id="n375"><data key="mechanism">mechanism-d4-b0-d3-b1-d2-b0</data></node><node id="n477"><data key="mechanism">mechanism-d4-b0-d3-b1-d2-b0-d1-b0</data></node><node id="n479"><data key="mechanism">mechanism-d4-b0-d3-b1-d2-b0-d1-b0-d0-b0</data></node><node id="n276"><data key="mechanism">mechanism-d4-b0-d3-b1-d2-b0-d1-b0-d0-b0</data></node><node id="n576"><data key="mechanism">mechanism-d4-b0-d3-b1-d2-b0-d1-b0-d0-b0</data></node><node id="n279"><data key="mechanism">mechanism-d4-b0-d3-b1-d2-b0-d1-b0-d0-b0</data></node><node id="n1060"><data key="mechanism">mechanism-d4-b0-d3-b1-d2-b0-d1-b0-d0-b0</data></node><node id="n975"><data key="mechanism">mechanism-d4-b0-d3-b1-d2-b0-d1-b0-d0-b0</data></node><node id="n282"><data key="mechanism">mechanism-d4-b0-d3-b1</data></node><node id="n281"><data key="mechanism">mechanism-d4-b0-d3-b1-d2-b0</data></node><node id="n767"><data key="mechanism">mechanism-d4-b0-d3-b1-d2-b0-d1-b0-d0-b0</data></node><node id="n768"><data key="mechanism">mechanism-d4-b0-d3-b1-d2-b0-d1-b0-d0-b0</data></node><node id="n463"><data key="mechanism">mechanism-d4-b0-d3-b1-d2-b0-d1-b0-d0-b0</data></node><node id="n367"><data key="mechanism">mechanism-d4-b0-d3-b1-d2-b0-d1-b0-d0-b0</data></node><node id="n1072"><data key="mechanism">mechanism-d4-b0-d3-b1-d2-b0-d1-b0-d0-b0</data></node><node id="n569"><data key="mechanism">mechanism-d4-b0-d3-b1-d2-b0-d1-b0-d0-b0</data></node><node id="n361"><data key="mechanism">mechanism-d4-b0-d3-b1-d2-b0-d1-b0-d0-b0</data></node><node id="n363"><data key="mechanism">mechanism-d4-b0-d3-b1-d2-b0-d1-b0-d0-b0</data></node><node id="n561"><data key="mechanism">mechanism-d4-b0-d3-b1-d2-b0-d1-b0-d0-b0</data></node><node id="n267"><data key="mechanism">mechanism-d4-b0-d3-b1-d2-b0</data></node><node id="n772"><data key="mechanism">mechanism-d4-b0-d3-b1-d2-b0-d1-b0-d0-b0</data></node><node id="n966"><data key="mechanism">mechanism-d4-b0-d3-b1-d2-b0-d1-b0-d0-b0</data></node><node id="n965"><data key="mechanism">mechanism-d4-b0-d3-b1-d2-b0-d1-b0-d0-b0</data></node><node id="n271"><data key="mechanism">mechanism-d4-b0-d3-b1-d2-b0-d1-b0</data></node><node id="n864"><data key="mechanism">mechanism-d4-b0-d3-b1-d2-b0-d1-b0-d0-b0</data></node><node id="n778"><data key="mechanism">mechanism-d4-b0-d3-b1-d2-b0-d1-b0-d0-b0</data></node><node id="n675"><data key="mechanism">mechanism-d4-b0-d3-b1-d2-b0</data></node><edge id="0" source="n1140" target="n820" label="b750ec41-924a-44cb-862a-821300fad74d"></edge><edge id="1" source="n299" target="n292" label="a9920183-9da8-461b-8e11-31d96c17d7ff"></edge><edge id="2" source="n758" target="n944" label="1a1d12ff-d756-4d4f-b39d-a417fb9ee22e"></edge><edge id="3" source="n756" target="n239" label="bfefd52d-dc96-460e-8d20-f761c9da42c5"></edge><edge id="4" source="n298" target="n576" label="d7082cbb-1134-4b5a-865f-b75badd7c8ae"></edge><edge id="5" source="n552" target="n886" label="9bef42c2-bfdf-479b-aec3-3eaf3cc123eb"></edge><edge id="6" source="n886" target="n804" label="f722d9e1-509e-4b56-bc2b-9f250ea8e485"></edge><edge id="7" source="n884" target="n445" label="31e7d5a7-fbf3-4abd-b788-ded85918d518"></edge><edge id="8" source="n613" target="n213" label="b2e2689d-a376-41de-b844-d73fe6a08593"></edge><edge id="9" source="n559" target="n1087" label="9992d592-032e-403e-bb67-2161dc9922a6"></edge><edge id="10" source="n411" target="n538" label="ecf050bf-5bfb-4ee9-8863-f6902028c4ce"></edge><edge id="11" source="n750" target="n426" label="774622e5-9c81-4451-adaf-ce6c98a604f0"></edge><edge id="12" source="n618" target="n772" label="4be90860-ec36-41d4-9c32-0b0815eec86e"></edge><edge id="13" source="n687" target="n951" label="2cd66350-b665-4cf9-b8d9-ffae4e0f07ff"></edge><edge id="14" source="n951" target="n1108" label="c1675deb-1cbf-48f8-a4a9-1b1dbc561c39"></edge><edge id="15" source="n213" target="n271" label="396e3a42-aff4-44b8-8eab-3fe334e15270"></edge><edge id="16" source="n619" target="n640" label="ace30d34-81ce-4d99-8ea5-38954ea79262"></edge><edge id="17" source="n813" target="n1060" label="8029bd90-156e-4f60-88e9-9ceac70d9fbd"></edge><edge id="18" source="n210" target="n411" label="137780d5-4cea-4544-ae3a-10de187fe8a4"></edge><edge id="19" source="n1147" target="n279" label="b2296191-a158-4d78-9579-863290fa4ac2"></edge><edge id="20" source="n353" target="n281" label="2a87af90-8179-432f-89e2-90c4153c9cbe"></edge><edge id="21" source="n496" target="n404" label="c6d2100e-69b1-429f-9371-28f43407b3fb"></edge><edge id="22" source="n409" target="n722" label="c07f4e52-4d18-4d61-ad6b-ed0a43ee5693"></edge><edge id="23" source="n407" target="n1147" label="1fb4451d-5093-4480-841a-da2e39cf4851"></edge><edge id="24" source="n749" target="n898" label="1992cf71-a0ea-4612-a45c-351326162c14"></edge><edge id="25" source="n406" target="n619" label="095c5d05-6ae6-4eab-a5ca-895a2f14629f"></edge><edge id="26" source="n405" target="n276" label="ce3d230b-bbf1-480e-8343-ab33ad10166c"></edge><edge id="27" source="n898" target="n545" label="fa9ed410-e3e4-4636-9589-5b72ca0535f5"></edge><edge id="28" source="n404" target="n552" label="37333a7d-d107-44ae-ac1e-974dcff2c267"></edge><edge id="29" source="n545" target="n241" label="d551a3a2-0fc1-409e-960f-ce9be81a30df"></edge><edge id="30" source="n804" target="n864" label="c14e7a1e-c0be-48e0-ad75-5f5435a8dc65"></edge><edge id="31" source="n693" target="n720" label="925c0249-2d56-4805-801b-4433fb53f029"></edge><edge id="32" source="n292" target="n754" label="a6bde134-a1db-463e-ab92-a36c087dc2ff"></edge><edge id="33" source="n489" target="n326" label="f1d7d030-38fb-4c43-b8fa-3b742731f79f"></edge><edge id="34" source="n176" target="n983" label="eafd6d2d-49ad-4493-98ab-da582b398541"></edge><edge id="35" source="n178" target="n375" label="0ee12e93-d9cd-482e-adc3-90df4ced3e6a"></edge><edge id="36" source="n944" target="n333" label="302150d4-051f-4463-9b1f-6399b7ac0525"></edge><edge id="37" source="n533" target="n724" label="8fef03b6-256f-4eec-a614-7dd55c60ef97"></edge><edge id="38" source="n532" target="n339" label="72d96115-fc69-441a-bf76-8fd326606f2c"></edge><edge id="39" source="n738" target="n505" label="5b74a07e-fd88-45c3-a1b7-f018f22ad05a"></edge><edge id="40" source="n538" target="n996" label="c14bca24-c14c-4273-a561-a28cc97db353"></edge><edge id="41" source="n1020" target="n518" label="7a388546-a55d-42cc-b683-a2162ad6b1eb"></edge><edge id="42" source="n731" target="n240" label="66a2ea29-73c6-4a08-8e6e-fa24c432f0ca"></edge><edge id="43" source="n636" target="n795" label="f3d32936-d54b-480b-b1dd-e96f0a4d2569"></edge><edge id="44" source="n434" target="n643" label="05208946-6cb1-495c-b3b1-0f0ba843a4d9"></edge><edge id="45" source="n1025" target="n738" label="866cd615-5ff2-4f4e-956b-cc5c74ea8e3a"></edge><edge id="46" source="n232" target="n966" label="2a109e96-094b-4195-945f-e56b3f0185dc"></edge><edge id="47" source="n836" target="n785" label="025b9da5-dc77-4141-a551-94ca2437e7b1"></edge><edge id="48" source="n339" target="n758" label="221d8b9c-155d-4176-b7c9-8d07bb11f051"></edge><edge id="49" source="n238" target="n1072" label="07e7f982-42c3-4361-ac1e-c5386f125917"></edge><edge id="50" source="n830" target="n221" label="d58be329-7966-44e1-8e14-1968b71104c1"></edge><edge id="51" source="n333" target="n602" label="78d51ecc-09f9-4dfc-a11d-d8f8f47269fb"></edge><edge id="52" source="n239" target="n965" label="44225219-b3ea-4a98-a052-2dcab66546d2"></edge><edge id="53" source="n722" target="n648" label="27ecee29-8418-41b2-b536-b89f831580b0"></edge><edge id="54" source="n426" target="n731" label="dcf0acf1-e45e-4fc6-9e12-e710e91f1d96"></edge><edge id="55" source="n728" target="n232" label="8e59e0e6-041f-478e-9a00-9fbd8db716b5"></edge><edge id="56" source="n429" target="n377" label="50f4170d-4176-446e-a548-f78afaff42c9"></edge><edge id="57" source="n720" target="n507" label="1db84f6c-7c7e-49d3-a783-d314a1035878"></edge><edge id="58" source="n221" target="n512" label="4b8aeaeb-01b6-4d8e-9171-572359460019"></edge><edge id="59" source="n826" target="n750" label="946d2952-e7c6-415e-8b3c-aa7bcac9ea36"></edge><edge id="60" source="n820" target="n396" label="30f5f71a-0bc3-4b3d-827e-39e468a4c67e"></edge><edge id="61" source="n822" target="n830" label="3ccb9a45-a2b7-4205-a394-31b5738710d1"></edge><edge id="62" source="n326" target="n756" label="a61a681b-95d1-4e0b-8937-bc6773feb7eb"></edge><edge id="63" source="n823" target="n517" label="04a97cd0-e76b-462e-a641-fe0a83106fa6"></edge><edge id="64" source="n921" target="n822" label="9bf81ecd-59b0-4975-a884-5e592f4a61f9"></edge><edge id="65" source="n197" target="n258" label="80ddc0f5-03ec-4b1c-a2bc-dedd766fdd4d"></edge><edge id="66" source="n199" target="n533" label="87a593b4-c439-44a2-b62c-e21fc3dc9add"></edge><edge id="67" source="n913" target="n298" label="f45feeac-0ec5-4424-81f5-dcff1587c8ae"></edge><edge id="68" source="n1087" target="n434" label="7098ffff-fba8-4bd7-97b8-0d5ccc52315a"></edge><edge id="69" source="n1118" target="n1001" label="06a8b70d-f46c-49c3-8abd-378e05975e7e"></edge><edge id="70" source="n396" target="n390" label="e5742019-faf4-4e53-9346-f1d55abf6be6"></edge><edge id="71" source="n915" target="n446" label="011eafd4-408a-4460-9216-b80b570553e5"></edge><edge id="72" source="n1086" target="n1096" label="84dbd6d6-b1db-4394-9885-1702c41ebff1"></edge><edge id="73" source="n258" target="n1137" label="ab911ae0-04cc-420b-b254-39007e8f35d1"></edge><edge id="74" source="n714" target="n299" label="59314c8e-2302-46fe-8b8e-b81fc36919e6"></edge><edge id="75" source="n715" target="n1118" label="adc40dec-2e36-4317-b97a-ba6a539079f8"></edge><edge id="76" source="n599" target="n1062" label="15d51be5-8256-4eaa-81f2-881e396a419b"></edge><edge id="77" source="n505" target="n569" label="42f89923-fd92-4c37-8bc8-029ed914080a"></edge><edge id="78" source="n648" target="n463" label="f8e6ec6c-9737-4921-9c1e-a43d56014ce8"></edge><edge id="79" source="n507" target="n767" label="60efd0e1-2840-4444-8fe5-08ee02744b9e"></edge><edge id="80" source="n785" target="n997" label="0eb87525-ea56-41cc-8d21-4da3603c0662"></edge><edge id="81" source="n1011" target="n884" label="e7e91fc7-1d7a-4b06-8c13-e02a28598481"></edge><edge id="82" source="n851" target="n709" label="2503909e-eac6-459b-b36f-467a6d632110"></edge><edge id="83" source="n850" target="n904" label="e8d79ca0-5453-4122-8ba4-c59436848531"></edge><edge id="84" source="n719" target="n618" label="7012cc22-24f8-405d-96a4-2ab443de0b8c"></edge><edge id="85" source="n1013" target="n1020" label="42296ee8-82b8-4261-8e45-47b30c08094f"></edge><edge id="86" source="n997" target="n267" label="baa7c363-f095-4b51-917e-21dc9095263f"></edge><edge id="87" source="n996" target="n249" label="3e6b8fb2-4214-4623-9888-97edb78b7d17"></edge><edge id="88" source="n643" target="n361" label="eda547ae-7eaa-407c-999a-95246557ab62"></edge><edge id="89" source="n640" target="n905" label="a8360c31-f47b-4a9e-a0e8-f635627eabcc"></edge><edge id="90" source="n859" target="n823" label="78022d35-29a4-4186-b315-51f53063d92e"></edge><edge id="91" source="n919" target="n429" label="2cc775bd-09c4-4a2f-b1e5-c1dc923ddc61"></edge><edge id="92" source="n1108" target="n197" label="5b8bfa33-2e31-48c5-870d-7da79be7e997"></edge><edge id="93" source="n904" target="n599" label="6c271641-90ac-4173-9f4c-75b17423a773"></edge><edge id="94" source="n445" target="n813" label="b4273331-30da-4609-8637-5d187fee693f"></edge><edge id="95" source="n1098" target="n921" label="f6710a20-a1fb-4d58-a0be-ec65aec629d3"></edge><edge id="96" source="n1096" target="n514" label="9a3697c6-4c2b-43b4-b7cf-8decee7a7079"></edge><edge id="97" source="n1103" target="n778" label="7ec3bd47-bbd5-4f19-934f-5c585499265b"></edge><edge id="98" source="n1093" target="n394" label="0a29aedd-8304-4c7c-b570-945fa2429721"></edge><edge id="99" source="n241" target="n915" label="52ad9ddc-464f-4a67-9093-1284abc0ca45"></edge><edge id="100" source="n587" target="n409" label="a4b72323-3591-48d4-ae3d-2672821a69f7"></edge><edge id="101" source="n240" target="n675" label="f266a660-8451-4afd-b956-2b6388e55b2d"></edge><edge id="102" source="n446" target="n1101" label="ccf9a650-4e85-4954-8773-133ffc054485"></edge><edge id="103" source="n518" target="n719" label="383f65af-7b12-4f9c-8d88-c13edec9fb84"></edge><edge id="104" source="n792" target="n843" label="cebaa8e4-ec36-41a4-b4a7-1cf63e59ae00"></edge><edge id="105" source="n517" target="n826" label="b450959d-1a34-410b-b411-2d7d02fab387"></edge><edge id="106" source="n794" target="n176" label="995c532b-dd3b-4691-9e5a-263191dd89e3"></edge><edge id="107" source="n1001" target="n1103" label="048b386f-abcf-4b9b-9536-fb10ebc7991d"></edge><edge id="108" source="n795" target="n613" label="4f187973-f7db-4f8d-b9df-71d19d3008e1"></edge><edge id="109" source="n512" target="n836" label="7250faf1-8c4f-4b2d-b341-4e7ee3095164"></edge><edge id="110" source="n709" target="n363" label="aca222a9-bad5-4486-8a28-c6f6e8a8e534"></edge><edge id="111" source="n513" target="n587" label="62125129-5d2a-4860-b5f3-7021b3f253f4"></edge><edge id="112" source="n843" target="n975" label="ace48f8c-0d21-45f4-a06f-17b44107c956"></edge><edge id="113" source="n1101" target="n1086" label="34e41285-1cf2-4fea-ad13-3a9d17626600"></edge><edge id="114" source="n984" target="n1025" label="ba8eff7d-6e10-44a0-a4b4-49928fbd57d1"></edge><edge id="115" source="n983" target="n698" label="089fcaca-4f62-411c-b125-8db06863c3f6"></edge><edge id="116" source="n390" target="n532" label="146ede12-1ca6-4d89-82ec-cea97e07d0ba"></edge><edge id="117" source="n908" target="n687" label="1e57fc35-0154-4146-9845-95b9e1c58b0a"></edge><edge id="118" source="n905" target="n1140" label="e2a0f0e1-dd15-435d-bed7-b9cd3e053335"></edge><edge id="119" source="n849" target="n407" label="bde7db0c-190c-48cb-996e-63ae3438aad6"></edge><edge id="120" source="n848" target="n559" label="66818127-ad63-42d3-92ad-4a80a075b52d"></edge><edge id="121" source="n1062" target="n353" label="f8dc70cc-aa9e-469f-b7a8-75a9af267de2"></edge><edge id="122" source="n1137" target="n693" label="e2030a59-aaa9-4616-a144-38d8c3047581"></edge><edge id="123" source="n377" target="n1098" label="b80bfbfa-22d8-4c76-87cd-c41878fb9fb5"></edge><edge id="124" source="n375" target="n246" label="58502838-2565-40a5-98b0-482f5a43344a"></edge><edge id="125" source="n477" target="n908" label="67a5de0f-bc87-4b3a-b355-a569b5b32f71"></edge><edge id="132" source="n479" target="n851" label="f4ed2d9c-3b7e-4100-bd73-89c6577718cf"></edge><edge id="127" source="n479" target="n282" label="c44b5886-1440-4721-8281-2a0d1f159090"></edge><edge id="134" source="n479" target="n1011" label="5931a72c-3ba1-4a3a-96be-e33bf8cb2d9c"></edge><edge id="126" source="n479" target="n859" label="55cfa356-09b9-48eb-8d22-f1c16bf01e8b"></edge><edge id="135" source="n479" target="n367" label="3585c6b3-dff7-402d-9af8-0999a81cd6d3"></edge><edge id="130" source="n479" target="n477" label="66387500-a959-493e-aac2-082e84faf87d"></edge><edge id="133" source="n479" target="n984" label="31110f1f-20bb-4947-94b4-af095cc6e356"></edge><edge id="129" source="n479" target="n406" label="6f6f9092-1369-461d-b7b4-5b1caf97ed8d"></edge><edge id="128" source="n479" target="n561" label="d47689b1-4c2f-4de9-b582-21f5cfa12634"></edge><edge id="137" source="n479" target="n850" label="9845b102-faf4-4e84-8c67-f208dc511afe"></edge><edge id="136" source="n479" target="n496" label="b45d0bfd-feb4-4aec-a71f-f392fda2fa1b"></edge><edge id="131" source="n479" target="n919" label="78ae2a8a-5c5a-4cdc-bef2-4ac698df07ae"></edge><edge id="138" source="n576" target="n178" label="1d74763d-83e5-4a0a-9699-88f0715fff18"></edge><edge id="139" source="n1060" target="n715" label="53e9ba59-32f8-4a39-b931-a476652c0c90"></edge><edge id="140" source="n975" target="n513" label="a80ebe38-ceb0-4c97-9689-9547c595cb22"></edge><edge id="141" source="n282" target="n792" label="46891c9c-0cec-4860-a634-e0b4ca664313"></edge><edge id="142" source="n281" target="n728" label="fc980e3f-6645-45de-aff7-e0e91a90c4db"></edge><edge id="143" source="n767" target="n818" label="eab628b6-5caa-4d08-a1e5-865b787beb1c"></edge><edge id="144" source="n768" target="n489" label="0fd2bfb0-6a09-4384-8fab-2ecac46faa49"></edge><edge id="145" source="n463" target="n714" label="8398b96a-6f96-47bd-ad55-a3b21c1f7f4e"></edge><edge id="146" source="n367" target="n636" label="9462d9e9-a83a-4bfc-ab48-a436d58cb786"></edge><edge id="147" source="n1072" target="n210" label="36610fe4-b69d-424d-a31c-508e0b3c7f64"></edge><edge id="148" source="n569" target="n848" label="d699406a-828d-4df2-a623-1963e362bab1"></edge><edge id="149" source="n361" target="n1093" label="e6672c18-55b0-4338-8ff2-708a7d3e20ee"></edge><edge id="150" source="n363" target="n749" label="501e222d-ce82-433f-a3de-e89dde42175d"></edge><edge id="151" source="n561" target="n768" label="f45ac1d6-9875-40ff-af8d-745ead6ba884"></edge><edge id="152" source="n267" target="n909" label="e1ed0952-820d-4773-bacb-b17419669dcb"></edge><edge id="153" source="n772" target="n405" label="d84917a2-0e63-4f69-a404-3f20bdfd03db"></edge><edge id="154" source="n966" target="n794" label="886513f8-4bf2-411a-92dd-1a5b54c0a55d"></edge><edge id="155" source="n965" target="n913" label="05e87e56-69e3-4f09-8dd7-6d81de9600d9"></edge><edge id="156" source="n271" target="n1013" label="0fd63543-e14c-46d3-8c12-f70d67a6ed98"></edge><edge id="157" source="n864" target="n238" label="4b899cd0-46e2-4fbb-9709-779a3785fe58"></edge><edge id="158" source="n778" target="n199" label="9069ddee-07d6-45b4-8258-7b151b199ffd"></edge><edge id="159" source="n675" target="n849" label="f78c718a-8969-47f1-9f95-46caaafee5b0"></edge></graph></graphml>