<?xml version="1.0" ?><graphml xmlns="http://graphml.graphdrawing.org/xmlns" xmlns:xsi="http://www.w3.org/2001/XMLSchema-instance" xsi:schemaLocation="http://graphml.graphdrawing.org/xmlns http://graphml.graphdrawing.org/xmlns/1.1/graphml.xsd"><key id="mechanism" for="node" attr.name="mechanism" attr.type="string"></key><graph id="G" edgedefault="directed"><node id="n735"><data key="mechanism">mechanism-d4-b0-d3-b0-d2-b0</data></node><node id="n299"><data key="mechanism">mechanism-d4-b0-d3-b2-d2-b0</data></node><node id="n757"><data key="mechanism">mechanism-d4-b0-d3-b2-d2-b0-d1-b0</data></node><node id="n579"><data key="mechanism">mechanism-d4-b0-d3-b0-d2-b1</data></node><node id="n107"><data key="mechanism">mechanism-d4-b0-d3-b0-d2-b0</data></node><node id="n102"><data key="mechanism">mechanism-d4-b0-d3-b0-d2-b0</data></node><node id="n557"><data key="mechanism">mechanism-d4-b0-d3-b0-d2-b0</data></node><node id="n479"><data key="mechanism">mechanism-d4-b0-d3-b0-d2-b0</data></node><node id="n818"><data key="mechanism">mechanism-d4-b0-d3-b0-d2-b1</data></node><node id="n1024"><data key="mechanism">mechanism-d4-b0-d3-b1-d2-b0</data></node><node id="n837"><data key="mechanism">mechanism-d4-b0-d3-b2-d2-b0</data></node><node id="n685"><data key="mechanism">mechanism-d4-b0-d3-b0-d2-b0</data></node><node id="n1011"><data key="mechanism">mechanism-d4-b0-d3-b0-d2-b0</data></node><node id="n143"><data key="mechanism">mechanism-d4-b0-d3-b2-d2-b0-d1-b0</data></node><node id="n783"><data key="mechanism">mechanism-d4-b0-d3-b2-d2-b0-d1-b0</data></node><node id="n643"><data key="mechanism">mechanism-d4-b0-d3-b2</data></node><node id="n238"><data key="mechanism">mechanism-d4-b0-d3-b0-d2-b0</data></node><node id="n353"><data key="mechanism">mechanism-d4-b0-d3-b2-d2-b0-d1-b0</data></node><node id="n990"><data key="mechanism">mechanism-d4-b0-d3-b0-d2-b1</data></node><node id="n927"><data key="mechanism">mechanism-d4-b0-d3-b2-d2-b0-d1-b0</data></node><node id="n724"><data key="mechanism">mechanism-d4-b0-d3-b1-d2-b0</data></node><node id="n440"><data key="mechanism">mechanism-d4-b0-d3-b0-d2-b0</data></node><node id="n181"><data key="mechanism">mechanism-d4-b0-d3-b2</data></node><node id="n287"><data key="mechanism">mechanism-d4-b0-d3-b1-d2-b1</data></node><node id="n583"><data key="mechanism">mechanism-d4-b0-d3-b0</data></node><node id="n705"><data key="mechanism">mechanism-d4-b0-d3-b2-d2-b0-d1-b0</data></node><node id="n113"><data key="mechanism">mechanism-d4-b0-d3-b2-d2-b0</data></node><node id="n720"><data key="mechanism">mechanism-d4-b0-d3-b1-d2-b1</data></node><node id="n269"><data key="mechanism">mechanism-d4-b0-d3-b2-d2-b0-d1-b0</data></node><node id="n695"><data key="mechanism">mechanism-d4-b0-d3-b2-d2-b0-d1-b0</data></node><node id="n1001"><data key="mechanism">mechanism-d4-b0-d3-b0-d2-b1</data></node><node id="n155"><data key="mechanism">mechanism-d4-b0-d3-b0-d2-b1</data></node><node id="n849"><data key="mechanism">mechanism-d4-b0-d3-b3</data></node><edge id="0" source="n735" target="n353" label="cc9d441d-8a10-4119-b2d9-5828196675d4"></edge><edge id="1" source="n299" target="n818" label="b88bc587-801d-43be-b45b-d17d85921000"></edge><edge id="2" source="n757" target="n849" label="c065ef6c-7f0e-47fb-9027-d231bba5d1b8"></edge><edge id="3" source="n579" target="n990" label="7b271ef8-da24-48a2-bc35-e197e74111ba"></edge><edge id="4" source="n107" target="n181" label="68277c8f-a0b3-47af-bd6f-54f3a50d9f95"></edge><edge id="5" source="n102" target="n1024" label="39b84751-e9b2-46c4-bd19-b301b6ae0ce7"></edge><edge id="6" source="n479" target="n238" label="a2b721fc-d560-47b4-a229-01c4202f6068"></edge><edge id="7" source="n818" target="n1011" label="ce07a28d-6b7b-429b-92f6-717b73847ed9"></edge><edge id="8" source="n1024" target="n143" label="36238006-1904-4fb8-b8bf-00ec12c13334"></edge><edge id="9" source="n685" target="n557" label="f13dbd11-3300-448c-830e-1769ea2b4984"></edge><edge id="10" source="n783" target="n579" label="6cf522ae-663c-415c-a785-af357350ac12"></edge><edge id="11" source="n643" target="n837" label="a009fcc2-70ce-4815-8658-06fe95018d98"></edge><edge id="12" source="n238" target="n695" label="f3c50004-ea92-496e-bb43-7ec12ee1a4aa"></edge><edge id="13" source="n353" target="n440" label="a92842f2-32c6-4d35-bfb1-9143235ff7d5"></edge><edge id="14" source="n990" target="n269" label="d536a83f-4ad8-4634-89e6-0c182750cb4e"></edge><edge id="15" source="n927" target="n113" label="ba00ff7c-10a1-4834-af4f-6c5aa8bda048"></edge><edge id="16" source="n724" target="n287" label="4efd91e5-4318-4d4a-babb-e84a0281aff9"></edge><edge id="17" source="n440" target="n583" label="5725331f-3047-4b5f-80f3-87faa6996623"></edge><edge id="18" source="n181" target="n757" label="f1b25afe-128a-4b11-aeb9-c222ccf6157d"></edge><edge id="22" source="n705" target="n720" label="74c60f83-a726-40a0-a6a4-a3badde285ab"></edge><edge id="27" source="n705" target="n479" label="e56f0faa-8496-43f3-bb12-77bf496250c8"></edge><edge id="23" source="n705" target="n1001" label="e2f1ee25-8982-4ebe-a563-086905af9b66"></edge><edge id="21" source="n705" target="n299" label="98a8ae25-0d1e-48fc-bf90-e5b506eca0ed"></edge><edge id="20" source="n705" target="n735" label="e8c9974f-3932-4b43-986e-4d5d5fb820f1"></edge><edge id="19" source="n705" target="n927" label="e95fd47b-8ad7-4e62-8cbf-69e5153546b0"></edge><edge id="26" source="n705" target="n107" label="9e3af6ba-fbfc-4e73-b893-5777c5541b27"></edge><edge id="24" source="n705" target="n102" label="20eacc85-5bbd-4ab1-9d8c-2b5a993da214"></edge><edge id="25" source="n705" target="n783" label="cb9238e6-594f-4a24-96b8-fb4bdf10170e"></edge><edge id="28" source="n113" target="n643" label="6fca0234-abb7-4098-b295-733aac702bca"></edge><edge id="29" source="n720" target="n155" label="4a444989-1383-4142-80b2-46435b783dd9"></edge><edge id="30" source="n1001" target="n724" label="912dc9a4-c38c-440b-a090-a830376c858a"></edge><edge id="31" source="n155" target="n685" label="4dd00637-3c0e-4db9-a2c5-7b300e585a46"></edge></graph></graphml>