<?xml version="1.0" ?><graphml xmlns="http://graphml.graphdrawing.org/xmlns" xmlns:xsi="http://www.w3.org/2001/XMLSchema-instance" xsi:schemaLocation="http://graphml.graphdrawing.org/xmlns http://graphml.graphdrawing.org/xmlns/1.1/graphml.xsd"><key id="mechanism" for="node" attr.name="mechanism" attr.type="string"></key><graph id="G" edgedefault="directed"><node id="n435"><data key="mechanism">mechanism-d4-b0-d3-b1</data></node><node id="n109"><data key="mechanism">mechanism-d4-b0-d3-b1</data></node><node id="n299"><data key="mechanism">mechanism-d4-b0-d3-b1</data></node><node id="n553"><data key="mechanism">mechanism-d4-b0-d3-b1</data></node><node id="n298"><data key="mechanism">mechanism-d4-b0-d3-b1</data></node><node id="n416"><data key="mechanism">mechanism-d4-b0-d3-b1</data></node><node id="n754"><data key="mechanism">mechanism-d4-b0-d3-b1</data></node><node id="n574"><data key="mechanism">mechanism-d4-b0-d3-b1</data></node><node id="n509"><data key="mechanism">mechanism-d4-b0-d3-b1</data></node><node id="n572"><data key="mechanism">mechanism-d4-b0-d3-b1</data></node><node id="n974"><data key="mechanism">mechanism-d4-b0-d3-b1</data></node><node id="n214"><data key="mechanism">mechanism-d4-b0-d3-b1</data></node><node id="n998"><data key="mechanism">mechanism-d4-b0-d3-b1</data></node><node id="n783"><data key="mechanism">mechanism-d4-b0-d3-b1</data></node><node id="n718"><data key="mechanism">mechanism-d4-b0-d3-b1</data></node><node id="n351"><data key="mechanism">mechanism-d4-b0-d3-b1</data></node><node id="n930"><data key="mechanism">mechanism-d4-b0-d3-b1</data></node><node id="n640"><data key="mechanism">mechanism-d4-b0-d3-b1</data></node><node id="n164"><data key="mechanism">mechanism-d4-b0-d3-b1</data></node><node id="n353"><data key="mechanism">mechanism-d4-b0-d3-b1</data></node><node id="n427"><data key="mechanism">mechanism-d4-b0-d3-b1</data></node><node id="n749"><data key="mechanism">mechanism-d4-b0-d3-b1</data></node><node id="n900"><data key="mechanism">mechanism-d4-b0-d3-b1</data></node><node id="n118"><data key="mechanism">mechanism-d4-b0-d3-b1</data></node><node id="n441"><data key="mechanism">mechanism-d4-b0-d3-b1</data></node><node id="n402"><data key="mechanism">mechanism-d4-b0-d3-b1</data></node><node id="n745"><data key="mechanism">mechanism-d4-b0-d3-b1</data></node><node id="n565"><data key="mechanism">mechanism-d4-b0-d3-b1</data></node><node id="n262"><data key="mechanism">mechanism-d4-b0-d3-b1</data></node><node id="n161"><data key="mechanism">mechanism-d4-b0-d3-b1</data></node><node id="n449"><data key="mechanism">mechanism-d4-b0-d3-b1</data></node><node id="n76"><data key="mechanism">mechanism-d4-b0-d3-b1</data></node><node id="n421"><data key="mechanism">mechanism-d4-b0-d3-b1</data></node><node id="n348"><data key="mechanism">mechanism-d4-b0-d3-b1</data></node><node id="n134"><data key="mechanism">mechanism-d4-b0-d3-b1</data></node><node id="n920"><data key="mechanism">mechanism-d4-b0-d3-b1</data></node><node id="n342"><data key="mechanism">mechanism-d4-b0-d3-b1</data></node><edge id="0" source="n435" target="n574" label="ffbf6813-82a4-424a-80d8-a026b4a77f4d"></edge><edge id="1" source="n109" target="n353" label="903ce380-1d5b-4c9f-a382-730259a779ca"></edge><edge id="2" source="n299" target="n348" label="24d60f73-3979-4826-91b4-e79e19948747"></edge><edge id="3" source="n553" target="n421" label="7ff3a095-1ffc-4599-ac96-38db43fb68dc"></edge><edge id="4" source="n298" target="n930" label="99d990d6-f1bc-4385-8a2a-4467d0f8d94d"></edge><edge id="5" source="n754" target="n134" label="5f488ed9-26f0-4bc6-bd75-58ea24d56441"></edge><edge id="6" source="n574" target="n214" label="ffa9c7cb-3d10-414f-8161-1fc4c8c2f8a6"></edge><edge id="7" source="n509" target="n640" label="bdb4503b-3fe4-4538-a3d1-d5e084ec7009"></edge><edge id="8" source="n572" target="n783" label="8c2eca8b-2b31-4430-9799-388e08e00b18"></edge><edge id="9" source="n998" target="n76" label="ad531c60-9ac6-4b41-814f-0fe31262587a"></edge><edge id="16" source="n351" target="n299" label="33d00437-44d9-410d-b1d4-bc605d217fbb"></edge><edge id="17" source="n351" target="n427" label="343d2e2c-b8c8-48bc-bc6e-7051c74cceac"></edge><edge id="13" source="n351" target="n262" label="2dfc00de-dc2a-414e-ae20-4593397843b3"></edge><edge id="10" source="n351" target="n998" label="8d56bb71-e798-4e2a-b655-968d2c8ab316"></edge><edge id="14" source="n351" target="n900" label="65314082-747a-4ca9-81c6-6a9f51ca75a0"></edge><edge id="11" source="n351" target="n118" label="c8c1b5f3-3b97-4f01-a1a4-794529c059a4"></edge><edge id="18" source="n351" target="n109" label="458f31d1-1b05-49a8-933f-db065a1da2f7"></edge><edge id="12" source="n351" target="n342" label="b20a09fe-c6cc-47ed-a3a2-5fc243ff8935"></edge><edge id="15" source="n351" target="n745" label="fb51143e-c0b1-4e80-9996-f61481ae9265"></edge><edge id="19" source="n930" target="n449" label="393d656a-a0b7-45eb-b719-6efbb17e035a"></edge><edge id="20" source="n640" target="n416" label="503f2e43-56e9-424a-b069-9304fbef961a"></edge><edge id="21" source="n164" target="n920" label="eb9010da-eeeb-41fc-bc39-a864a1ff93db"></edge><edge id="22" source="n353" target="n164" label="23a41ed6-6c21-45b4-a02b-d2d9f2368ffc"></edge><edge id="23" source="n427" target="n402" label="86146e2c-b06f-453d-b0f9-b45a1ab1fea5"></edge><edge id="24" source="n749" target="n974" label="16965bd8-9cde-4b38-a6fd-8736acdb2f0a"></edge><edge id="25" source="n900" target="n298" label="65c05a85-ea77-479b-9461-04ae6f4c4fdd"></edge><edge id="26" source="n118" target="n441" label="375b787b-d220-4da7-b3e3-b09186408c2d"></edge><edge id="27" source="n441" target="n572" label="08dc57cc-2c99-4b9f-8f8e-8bb37c3261a3"></edge><edge id="28" source="n402" target="n754" label="717eabfb-33f2-446d-9181-c972390c0193"></edge><edge id="29" source="n745" target="n435" label="cdec8ed0-6916-4229-91f4-5c9b6531b6fd"></edge><edge id="30" source="n565" target="n718" label="223e713e-3238-41b3-9f57-30b8c8d8a880"></edge><edge id="31" source="n262" target="n509" label="613f94c5-abcc-4509-9dda-0ea48a95616a"></edge><edge id="32" source="n161" target="n553" label="562fd0a7-e494-4b2b-9ff7-bd3cb3a67528"></edge><edge id="33" source="n76" target="n749" label="e6be1d95-7305-4772-93e1-beb97cf69cec"></edge><edge id="34" source="n348" target="n565" label="c8218589-1d7b-45b9-b7f6-897c309ad55e"></edge><edge id="35" source="n342" target="n161" label="453eb94a-e1c7-4544-8574-5ea3c8c88d77"></edge></graph></graphml>