<?xml version="1.0" ?><graphml xmlns="http://graphml.graphdrawing.org/xmlns" xmlns:xsi="http://www.w3.org/2001/XMLSchema-instance" xsi:schemaLocation="http://graphml.graphdrawing.org/xmlns http://graphml.graphdrawing.org/xmlns/1.1/graphml.xsd"><key id="mechanism" for="node" attr.name="mechanism" attr.type="string"></key><graph id="G" edgedefault="directed"><node id="n41"><data key="mechanism">mechanism-d4-b0-d3-b1-d2-b0-d1-b0</data></node><node id="n122"><data key="mechanism">mechanism-d4-b0-d3-b1-d2-b0</data></node><node id="n44"><data key="mechanism">mechanism-d4-b1-d3-b1-d2-b0-d1-b0-d0-b0</data></node><node id="n804"><data key="mechanism">mechanism-d4-b0-d3-b1-d2-b0-d1-b0-d0-b0</data></node><node id="n909"><data key="mechanism">mechanism-d4-b1-d3-b1-d2-b0-d1-b0-d0-b0</data></node><node id="n603"><data key="mechanism">mechanism-d4-b1-d3-b1-d2-b0-d1-b0-d0-b0</data></node><node id="n112"><data key="mechanism">mechanism-d4-b0-d3-b1-d2-b0-d1-b0-d0-b0</data></node><edge id="5" source="n112" target="n44" label="49a7fd53-dc3c-4fb6-b51c-984a44ec07c1"></edge><edge id="1" source="n112" target="n603" label="e82e4198-d744-480b-a9e3-a4c3ecc3612a"></edge><edge id="4" source="n112" target="n122" label="cedc0e16-c39f-4454-a59f-eaf31eee91fd"></edge><edge id="3" source="n112" target="n804" label="4f875751-eeed-42ec-b87d-9581b7429827"></edge><edge id="0" source="n112" target="n909" label="1ce25b2d-fded-4e41-b3fa-877f70595819"></edge><edge id="2" source="n112" target="n41" label="6b8dbcf9-a996-4a17-82dd-019427d9b955"></edge></graph></graphml>