<?xml version="1.0" ?><graphml xmlns="http://graphml.graphdrawing.org/xmlns" xmlns:xsi="http://www.w3.org/2001/XMLSchema-instance" xsi:schemaLocation="http://graphml.graphdrawing.org/xmlns http://graphml.graphdrawing.org/xmlns/1.1/graphml.xsd"><key id="mechanism" for="node" attr.name="mechanism" attr.type="string"></key><graph id="G" edgedefault="directed"><node id="n436"><data key="mechanism">mechanism-d4-b0-d3-b1-d2-b0-d1-b0</data></node><node id="n195"><data key="mechanism">mechanism-d4-b1-d3-b1-d2-b0</data></node><node id="n133"><data key="mechanism">mechanism-d4-b0-d3-b1-d2-b0</data></node><node id="n949"><data key="mechanism">mechanism-d4-b0-d3-b1-d2-b0-d1-b0-d0-b0</data></node><node id="n741"><data key="mechanism">mechanism-d4-b1-d3-b1-d2-b0-d1-b0-d0-b0</data></node><node id="n496"><data key="mechanism">mechanism-d4-b0-d3-b1-d2-b0-d1-b0-d0-b0</data></node><edge id="4" source="n436" target="n133" label="bb150ba4-ef8f-47fe-9249-cbd94bc75b45"></edge><edge id="1" source="n436" target="n496" label="e3e4d16d-cee5-4311-8d4d-d587ff3d803e"></edge><edge id="3" source="n436" target="n741" label="c965a9b8-91a0-4cc9-a2a9-6777321e0bed"></edge><edge id="2" source="n436" target="n195" label="208856c6-42bd-426b-9998-0d5959705c0f"></edge><edge id="0" source="n436" target="n949" label="25fc3a3d-3544-4aa1-ad8a-4f88b880404a"></edge></graph></graphml>