<?xml version="1.0" ?><graphml xmlns="http://graphml.graphdrawing.org/xmlns" xmlns:xsi="http://www.w3.org/2001/XMLSchema-instance" xsi:schemaLocation="http://graphml.graphdrawing.org/xmlns http://graphml.graphdrawing.org/xmlns/1.1/graphml.xsd"><key id="mechanism" for="node" attr.name="mechanism" attr.type="string"></key><graph id="G" edgedefault="directed"><node id="n395"><data key="mechanism">mechanism-d4-b0-d3-b1-d2-b0-d1-b0</data></node><node id="n871"><data key="mechanism">mechanism-d4-b0-d3-b1-d2-b0-d1-b0</data></node><node id="n105"><data key="mechanism">mechanism-d4-b1-d3-b1-d2-b0-d1-b0-d0-b0</data></node><node id="n1005"><data key="mechanism">mechanism-d4-b1-d3-b1-d2-b0-d1-b0</data></node><node id="n932"><data key="mechanism">mechanism-d4-b0-d3-b1-d2-b0-d1-b0-d0-b0</data></node><node id="n323"><data key="mechanism">mechanism-d4-b1-d3-b1-d2-b0</data></node><node id="n994"><data key="mechanism">mechanism-d4-b1-d3-b1-d2-b0</data></node><node id="n139"><data key="mechanism">mechanism-d4-b0-d3-b1-d2-b0-d1-b0-d0-b0</data></node><node id="n595"><data key="mechanism">mechanism-d4-b1-d3-b1-d2-b0-d1-b0-d0-b0</data></node><node id="n217"><data key="mechanism">mechanism-d4-b1-d3-b1-d2-b0-d1-b0</data></node><node id="n198"><data key="mechanism">mechanism-d4-b1-d3-b1</data></node><node id="n523"><data key="mechanism">mechanism-d4-b1-d3-b1-d2-b0</data></node><edge id="6" source="n105" target="n1005" label="caff9ba7-c480-4967-a259-8aa29e9d9a6d"></edge><edge id="3" source="n105" target="n217" label="ca9e937e-4b83-45fe-9bea-36bc6be85df2"></edge><edge id="0" source="n105" target="n139" label="ef533446-d071-4588-9a9c-27727c8309e4"></edge><edge id="5" source="n105" target="n994" label="0c61b108-2a60-49f3-87dd-9b2d7004f7fc"></edge><edge id="4" source="n105" target="n323" label="0c486ee4-a19e-4388-8622-fbc0d8dae69d"></edge><edge id="1" source="n105" target="n523" label="a4a705cf-e0ca-4efd-8da5-18271efa883e"></edge><edge id="2" source="n105" target="n395" label="319163cd-5429-4a4c-85fb-debb59209c11"></edge><edge id="7" source="n1005" target="n871" label="3fbde840-9dfa-408a-9586-898e96309774"></edge><edge id="8" source="n323" target="n932" label="a27caff2-da9c-4ab6-9fff-6751dcffe0e1"></edge><edge id="9" source="n139" target="n198" label="5dc811cd-22df-402d-8dfa-56e1c102bbbe"></edge><edge id="10" source="n217" target="n595" label="5e5906c0-e12d-4b7e-8926-fad43a849b15"></edge></graph></graphml>