<?xml version="1.0" ?><graphml xmlns="http://graphml.graphdrawing.org/xmlns" xmlns:xsi="http://www.w3.org/2001/XMLSchema-instance" xsi:schemaLocation="http://graphml.graphdrawing.org/xmlns http://graphml.graphdrawing.org/xmlns/1.1/graphml.xsd"><key id="mechanism" for="node" attr.name="mechanism" attr.type="string"></key><graph id="G" edgedefault="directed"><node id="n454"><data key="mechanism">mechanism-d4-b0-d3-b1-d2-b1-d1-b0</data></node><node id="n912"><data key="mechanism">mechanism-d4-b0-d3-b1-d2-b0-d1-b0</data></node><node id="n550"><data key="mechanism">mechanism-d4-b0-d3-b1</data></node><node id="n191"><data key="mechanism">mechanism-d4-b0-d3-b1-d2-b1-d1-b0</data></node><node id="n416"><data key="mechanism">mechanism-d4-b0-d3-b1-d2-b0</data></node><node id="n259"><data key="mechanism">mechanism-d4-b0-d3-b1-d2-b0</data></node><node id="n885"><data key="mechanism">mechanism-d4-b0-d3-b1-d2-b0-d1-b0</data></node><node id="n818"><data key="mechanism">mechanism-d4-b0-d3-b1-d2-b1-d1-b0</data></node><node id="n279"><data key="mechanism">mechanism-d4-b0-d3-b1-d2-b0</data></node><node id="n977"><data key="mechanism">mechanism-d4-b0-d3-b1-d2-b0-d1-b0</data></node><node id="n669"><data key="mechanism">mechanism-d4-b0-d3-b1</data></node><node id="n336"><data key="mechanism">mechanism-d4-b0-d3-b1-d2-b0-d1-b0</data></node><node id="n1010"><data key="mechanism">mechanism-d4-b0-d3-b1-d2-b0-d1-b0</data></node><node id="n814"><data key="mechanism">mechanism-d4-b0-d3-b1-d2-b0-d1-b0</data></node><node id="n957"><data key="mechanism">mechanism-d4-b0-d3-b1-d2-b0</data></node><node id="n875"><data key="mechanism">mechanism-d4-b0-d3-b1-d2-b0</data></node><node id="n462"><data key="mechanism">mechanism-d4-b0-d3-b1-d2-b0-d1-b0</data></node><node id="n409"><data key="mechanism">mechanism-d4-b0-d3-b1-d2-b0</data></node><node id="n443"><data key="mechanism">mechanism-d4-b0-d3-b1-d2-b0-d1-b0</data></node><node id="n180"><data key="mechanism">mechanism-d4-b0-d3-b1-d2-b1-d1-b0</data></node><node id="n284"><data key="mechanism">mechanism-d4-b0-d3-b1-d2-b1-d1-b0</data></node><node id="n464"><data key="mechanism">mechanism-d4-b0-d3-b1-d2-b1-d1-b0</data></node><node id="n428"><data key="mechanism">mechanism-d4-b0-d3-b1-d2-b0-d1-b0</data></node><node id="n568"><data key="mechanism">mechanism-d4-b0-d3-b1-d2-b0-d1-b0</data></node><node id="n584"><data key="mechanism">mechanism-d4-b0-d3-b1-d2-b0</data></node><node id="n1031"><data key="mechanism">mechanism-d4-b0-d3-b1-d2-b0</data></node><node id="n56"><data key="mechanism">mechanism-d4-b0-d3-b1-d2-b1-d1-b0</data></node><node id="n564"><data key="mechanism">mechanism-d4-b0-d3-b1-d2-b0</data></node><node id="n423"><data key="mechanism">mechanism-d4-b0-d3-b1-d2-b0-d1-b0</data></node><node id="n78"><data key="mechanism">mechanism-d4-b0-d3-b1-d2-b0</data></node><node id="n824"><data key="mechanism">mechanism-d4-b0-d3-b1-d2-b1-d1-b0</data></node><node id="n772"><data key="mechanism">mechanism-d4-b0-d3-b1-d2-b0-d1-b0</data></node><node id="n707"><data key="mechanism">mechanism-d4-b0-d3-b1-d2-b1-d1-b0</data></node><node id="n370"><data key="mechanism">mechanism-d4-b0-d3-b1-d2-b0-d1-b0</data></node><node id="n391"><data key="mechanism">mechanism-d4-b0-d3-b1-d2-b0-d1-b0</data></node><node id="n779"><data key="mechanism">mechanism-d4-b0-d3-b1-d2-b1-d1-b0</data></node><node id="n944"><data key="mechanism">mechanism-d4-b0-d3-b1-d2-b1-d1-b0</data></node><edge id="1" source="n454" target="n772" label="29d4a1e9-3354-457e-8e62-4546d50c5013"></edge><edge id="5" source="n454" target="n824" label="c25e63d7-cab2-4874-803d-5ea36d73fb6c"></edge><edge id="4" source="n454" target="n336" label="105c2e47-85ef-4bc8-a6e9-2e4f85b0dc62"></edge><edge id="0" source="n454" target="n814" label="6f8a7bfe-63d2-48dc-8716-88c301197586"></edge><edge id="7" source="n454" target="n779" label="74fde5cc-d2a6-439c-83d3-236027e1befa"></edge><edge id="2" source="n454" target="n584" label="d3949c47-2fc3-4bc8-83a4-02ba22ffe99b"></edge><edge id="8" source="n454" target="n191" label="aff1aa9d-83e9-4703-b03d-fea004cf4376"></edge><edge id="6" source="n454" target="n944" label="d9837bec-3cdb-46e4-ab3f-e7a5c8d4e117"></edge><edge id="3" source="n454" target="n78" label="02294c3d-1de4-4e62-83b4-409164e3eaeb"></edge><edge id="9" source="n912" target="n818" label="21cce773-70a5-4568-813b-1d6790b6acc1"></edge><edge id="10" source="n550" target="n443" label="96b0428c-a0e0-4d56-836e-bd667a8eac45"></edge><edge id="11" source="n191" target="n56" label="a87012ae-2e03-4c74-9efa-9c91ddfb8026"></edge><edge id="12" source="n885" target="n416" label="73149801-cb1d-486d-abb0-824e96280589"></edge><edge id="13" source="n818" target="n180" label="515baf9e-61a9-403e-b3b6-b0d32f9173fa"></edge><edge id="14" source="n336" target="n409" label="1a01e2ec-cdaa-45e8-b981-7973cb4eb361"></edge><edge id="15" source="n1010" target="n428" label="10e0e324-73a5-4782-a407-d67c3b645251"></edge><edge id="16" source="n814" target="n707" label="612447cd-0658-4135-9fd4-a2cf82b70c36"></edge><edge id="17" source="n957" target="n1031" label="df665ac8-3d02-4102-b862-ec8a8e21f105"></edge><edge id="18" source="n875" target="n464" label="5d0e0bb5-811c-48c6-a284-1b30d2a57011"></edge><edge id="19" source="n462" target="n977" label="9b5629ca-b414-49ee-820c-4536cd921a05"></edge><edge id="20" source="n409" target="n885" label="512a37e8-1912-4301-b928-75305be995a0"></edge><edge id="21" source="n443" target="n423" label="c4699a68-99c7-41e1-8ba9-ed18b8d7aa3a"></edge><edge id="22" source="n284" target="n462" label="25d6c15b-569b-4f46-939e-a8cc14a5b111"></edge><edge id="23" source="n568" target="n279" label="00052afb-2a3a-4671-b326-af0f6beb67df"></edge><edge id="24" source="n584" target="n912" label="c9b6a5d8-ebb7-4eae-b523-9d1d7a35d4c6"></edge><edge id="25" source="n1031" target="n259" label="285997ef-eb33-4103-8f18-b8cad8f1484b"></edge><edge id="26" source="n56" target="n875" label="5d73360d-ca35-47c3-b277-a1bb762a5c37"></edge><edge id="27" source="n564" target="n669" label="f59c927b-dc81-45b4-860e-ccd276229a6f"></edge><edge id="28" source="n78" target="n550" label="5f2b7a0d-7a32-4600-beb7-3c35643da840"></edge><edge id="29" source="n824" target="n370" label="c2316e18-5ea8-4bf2-9154-5f154db9ae32"></edge><edge id="30" source="n772" target="n284" label="fd29b5f9-b903-4773-bdcc-9d5b6fad248d"></edge><edge id="31" source="n707" target="n564" label="3415ab7a-6d30-4fed-ae54-721ae87ff27c"></edge><edge id="32" source="n370" target="n568" label="63086b1f-f303-405f-a7ff-949198ba7f3e"></edge><edge id="33" source="n391" target="n1010" label="eb9ea580-db20-473e-aedd-00728a987c3a"></edge><edge id="34" source="n779" target="n391" label="2bc184bf-8ddd-4539-99e9-3d5505b5dad9"></edge><edge id="35" source="n944" target="n957" label="1a08b469-e28c-40ba-a29b-720d68cd4abc"></edge></graph></graphml>