<?xml version="1.0" ?><graphml xmlns="http://graphml.graphdrawing.org/xmlns" xmlns:xsi="http://www.w3.org/2001/XMLSchema-instance" xsi:schemaLocation="http://graphml.graphdrawing.org/xmlns http://graphml.graphdrawing.org/xmlns/1.1/graphml.xsd"><key id="mechanism" for="node" attr.name="mechanism" attr.type="string"></key><graph id="G" edgedefault="directed"><node id="n173"><data key="mechanism">mechanism-d4-b0-d3-b1</data></node><node id="n171"><data key="mechanism">mechanism-d4-b0-d3-b1</data></node><node id="n754"><data key="mechanism">mechanism-d4-b0-d3-b1</data></node><node id="n1014"><data key="mechanism">mechanism-d4-b0-d3-b1</data></node><node id="n753"><data key="mechanism">mechanism-d4-b0-d3-b1</data></node><node id="n1015"><data key="mechanism">mechanism-d4-b0-d3-b1</data></node><node id="n593"><data key="mechanism">mechanism-d4-b0-d3-b1</data></node><node id="n558"><data key="mechanism">mechanism-d4-b0-d3-b1</data></node><node id="n817"><data key="mechanism">mechanism-d4-b0-d3-b1</data></node><node id="n253"><data key="mechanism">mechanism-d4-b0-d3-b1</data></node><node id="n86"><data key="mechanism">mechanism-d4-b0-d3-b1</data></node><node id="n616"><data key="mechanism">mechanism-d4-b0-d3-b1</data></node><node id="n615"><data key="mechanism">mechanism-d4-b0-d3-b1</data></node><node id="n505"><data key="mechanism">mechanism-d4-b0-d3-b1</data></node><node id="n950"><data key="mechanism">mechanism-d4-b0-d3-b1</data></node><node id="n644"><data key="mechanism">mechanism-d4-b0-d3-b1</data></node><node id="n719"><data key="mechanism">mechanism-d4-b0-d3-b1</data></node><node id="n96"><data key="mechanism">mechanism-d4-b0-d3-b1</data></node><node id="n314"><data key="mechanism">mechanism-d4-b0-d3-b1</data></node><node id="n494"><data key="mechanism">mechanism-d4-b0-d3-b1</data></node><node id="n97"><data key="mechanism">mechanism-d4-b0-d3-b1</data></node><node id="n444"><data key="mechanism">mechanism-d4-b0-d3-b1</data></node><node id="n408"><data key="mechanism">mechanism-d4-b0-d3-b1</data></node><node id="n406"><data key="mechanism">mechanism-d4-b0-d3-b1</data></node><node id="n899"><data key="mechanism">mechanism-d4-b0-d3-b1</data></node><node id="n806"><data key="mechanism">mechanism-d4-b0-d3-b1</data></node><node id="n587"><data key="mechanism">mechanism-d4-b0-d3-b1</data></node><node id="n605"><data key="mechanism">mechanism-d4-b0-d3-b1</data></node><node id="n131"><data key="mechanism">mechanism-d4-b0-d3-b1</data></node><node id="n792"><data key="mechanism">mechanism-d4-b0-d3-b1</data></node><node id="n802"><data key="mechanism">mechanism-d4-b0-d3-b1</data></node><node id="n300"><data key="mechanism">mechanism-d4-b0-d3-b1</data></node><node id="n275"><data key="mechanism">mechanism-d4-b0-d3-b1</data></node><node id="n1020"><data key="mechanism">mechanism-d4-b0-d3-b1</data></node><node id="n832"><data key="mechanism">mechanism-d4-b0-d3-b1</data></node><node id="n932"><data key="mechanism">mechanism-d4-b0-d3-b1</data></node><node id="n930"><data key="mechanism">mechanism-d4-b0-d3-b1</data></node><node id="n662"><data key="mechanism">mechanism-d4-b0-d3-b1</data></node><node id="n621"><data key="mechanism">mechanism-d4-b0-d3-b1</data></node><node id="n620"><data key="mechanism">mechanism-d4-b0-d3-b1</data></node><node id="n424"><data key="mechanism">mechanism-d4-b0-d3-b1</data></node><node id="n566"><data key="mechanism">mechanism-d4-b0-d3-b1</data></node><node id="n563"><data key="mechanism">mechanism-d4-b0-d3-b1</data></node><node id="n110"><data key="mechanism">mechanism-d4-b0-d3-b1</data></node><node id="n420"><data key="mechanism">mechanism-d4-b0-d3-b1</data></node><node id="n224"><data key="mechanism">mechanism-d4-b0-d3-b1</data></node><node id="n155"><data key="mechanism">mechanism-d4-b0-d3-b1</data></node><node id="n223"><data key="mechanism">mechanism-d4-b0-d3-b1</data></node><node id="n920"><data key="mechanism">mechanism-d4-b0-d3-b1</data></node><node id="n371"><data key="mechanism">mechanism-d4-b0-d3-b1</data></node><node id="n922"><data key="mechanism">mechanism-d4-b0-d3-b1</data></node><node id="n673"><data key="mechanism">mechanism-d4-b0-d3-b1</data></node><node id="n674"><data key="mechanism">mechanism-d4-b0-d3-b1</data></node><edge id="0" source="n171" target="n97" label="d5c0179f-0902-4cbf-8103-c3b98985b973"></edge><edge id="1" source="n754" target="n930" label="e167a803-e1b4-487e-ad17-27d85ee9349e"></edge><edge id="14" source="n1014" target="n719" label="b34448e7-d416-412f-814b-8694674772a2"></edge><edge id="13" source="n1014" target="n155" label="f624131d-51f5-4bf2-a6c5-c05b46b4c1c5"></edge><edge id="11" source="n1014" target="n593" label="e97ea5c4-00d8-47ea-b11b-919344566647"></edge><edge id="12" source="n1014" target="n300" label="588f1eae-5ec5-41e1-9d88-249a6c714d2c"></edge><edge id="8" source="n1014" target="n615" label="6a7dace7-fb3f-44be-b423-e479ebdd3c4e"></edge><edge id="5" source="n1014" target="n817" label="1d8b6333-9da3-4f72-b01f-94da11eb4426"></edge><edge id="10" source="n1014" target="n566" label="089065c9-9c82-4127-8658-02e6c0130331"></edge><edge id="9" source="n1014" target="n563" label="dd3e7003-a445-4ee0-95b4-075ae85351fa"></edge><edge id="2" source="n1014" target="n408" label="6be5eff1-e680-45dd-8fcf-e8121c39c2af"></edge><edge id="7" source="n1014" target="n587" label="bf8410db-82f4-4a6d-8aed-03c92a646d1d"></edge><edge id="6" source="n1014" target="n932" label="79199c53-2aeb-49f9-b68c-d3f8260c7c01"></edge><edge id="4" source="n1014" target="n753" label="58f83a40-dae8-493d-a4d5-dbb2bd8fd1ce"></edge><edge id="3" source="n1014" target="n110" label="d666e561-d8bd-4cc3-94ab-b33f2edfddf0"></edge><edge id="15" source="n753" target="n406" label="7c2baedd-adc5-4827-a7a7-aa6f5fd53221"></edge><edge id="16" source="n1015" target="n558" label="c1a8c924-364b-4a5a-863f-100e802657d9"></edge><edge id="17" source="n593" target="n673" label="cc7eba20-81ed-43b7-8300-d0b3b8483caa"></edge><edge id="18" source="n817" target="n444" label="3505de92-9c52-4666-b789-1fd5006beb69"></edge><edge id="19" source="n253" target="n371" label="ffb3875e-79ae-406f-820a-3256a920e074"></edge><edge id="20" source="n86" target="n1020" label="0b164a22-118e-4acb-85ac-72d799e21b68"></edge><edge id="21" source="n616" target="n314" label="a27c79da-b196-40ca-a218-57037c7b1fe1"></edge><edge id="22" source="n615" target="n662" label="375c48cd-065e-4a6d-9842-bf5d465640f7"></edge><edge id="23" source="n505" target="n96" label="29c05b6f-89b7-4769-ab20-c6f9c6abea62"></edge><edge id="24" source="n719" target="n131" label="27fda05b-b860-476b-9bf9-5b404b15fefc"></edge><edge id="25" source="n96" target="n620" label="0f7b3108-ecc8-4c49-aacd-e23a5eadaa7c"></edge><edge id="26" source="n494" target="n644" label="42d2d922-225f-4eee-808c-3036ed707bb4"></edge><edge id="27" source="n444" target="n754" label="a8c561ba-832f-4633-9d24-8892e7d2dc00"></edge><edge id="28" source="n408" target="n832" label="cb4397e1-c99d-4f40-a58f-bacc002ec7f8"></edge><edge id="29" source="n406" target="n920" label="62d9a87a-09dc-4d54-884e-251bc3ff4fb4"></edge><edge id="30" source="n899" target="n616" label="6cd3f715-6a5e-4906-8633-684e6ec745b8"></edge><edge id="31" source="n806" target="n621" label="dc369682-09b7-4368-b843-fc7a4240a3b2"></edge><edge id="32" source="n587" target="n922" label="9dd5b664-7bf1-4c6b-9ac6-d9685363dce0"></edge><edge id="33" source="n131" target="n223" label="54222d1e-0f9a-46bd-8341-560347551143"></edge><edge id="34" source="n802" target="n792" label="43132014-58f9-4ec6-bb55-604512a07dfc"></edge><edge id="35" source="n300" target="n275" label="a437a8ac-6e60-4556-85ad-029fc8b3b6ba"></edge><edge id="36" source="n275" target="n171" label="fd0fd57a-f48b-4734-b689-ae2bb41083d3"></edge><edge id="37" source="n832" target="n420" label="849cb2a3-a4a2-4062-92ac-fe4562aa2584"></edge><edge id="38" source="n932" target="n899" label="30989283-7769-465a-9d38-8b897dd2ac55"></edge><edge id="39" source="n662" target="n494" label="3d4ce043-394a-4a3c-806c-24fe8b85e6a4"></edge><edge id="40" source="n424" target="n806" label="abc9a4a7-8923-4472-ab5e-c6e0910ca6e5"></edge><edge id="41" source="n566" target="n505" label="4ad541eb-63c7-41d5-9810-78552b14c2c9"></edge><edge id="42" source="n563" target="n424" label="d32e21b9-4054-4934-aa11-91f3f09a220b"></edge><edge id="43" source="n110" target="n253" label="d2f950b3-18e8-4e9b-9ff7-bd00744f0f60"></edge><edge id="44" source="n420" target="n605" label="cc98212e-72a2-4a74-9153-c143f3068d74"></edge><edge id="45" source="n224" target="n802" label="3b489ee2-7964-4016-b269-308dea8645e8"></edge><edge id="46" source="n155" target="n224" label="61bc66f0-c466-4b61-bcc8-9407e5afeebc"></edge><edge id="47" source="n223" target="n173" label="2fc502a1-9a46-4371-9aa2-59c3b326551e"></edge><edge id="48" source="n920" target="n950" label="8ee34344-05dd-4520-ae2c-e71a5b56e945"></edge><edge id="49" source="n371" target="n674" label="4dbf7352-a68e-4338-99f6-5d924679ad08"></edge><edge id="50" source="n922" target="n86" label="78473141-8622-4e3f-b0d3-a9e98cce6a16"></edge><edge id="51" source="n673" target="n1015" label="f06eb739-9fbf-4f28-a12f-49afd0207baa"></edge></graph></graphml>