<?xml version="1.0" ?><graphml xmlns="http://graphml.graphdrawing.org/xmlns" xmlns:xsi="http://www.w3.org/2001/XMLSchema-instance" xsi:schemaLocation="http://graphml.graphdrawing.org/xmlns http://graphml.graphdrawing.org/xmlns/1.1/graphml.xsd"><key id="mechanism" for="node" attr.name="mechanism" attr.type="string"></key><graph id="G" edgedefault="directed"><node id="n454"><data key="mechanism">mechanism-d4-b0-d3-b1</data></node><node id="n912"><data key="mechanism">mechanism-d4-b0-d3-b1</data></node><node id="n298"><data key="mechanism">mechanism-d4-b0-d3-b1</data></node><node id="n552"><data key="mechanism">mechanism-d4-b0-d3-b1</data></node><node id="n716"><data key="mechanism">mechanism-d4-b0-d3-b1</data></node><node id="n751"><data key="mechanism">mechanism-d4-b0-d3-b1</data></node><node id="n83"><data key="mechanism">mechanism-d4-b0-d3-b1</data></node><node id="n852"><data key="mechanism">mechanism-d4-b0-d3-b1</data></node><node id="n998"><data key="mechanism">mechanism-d4-b0-d3-b1</data></node><node id="n647"><data key="mechanism">mechanism-d4-b0-d3-b1</data></node><node id="n1013"><data key="mechanism">mechanism-d4-b0-d3-b1</data></node><node id="n642"><data key="mechanism">mechanism-d4-b0-d3-b1</data></node><node id="n169"><data key="mechanism">mechanism-d4-b0-d3-b1</data></node><node id="n318"><data key="mechanism">mechanism-d4-b0-d3-b1</data></node><node id="n493"><data key="mechanism">mechanism-d4-b0-d3-b1</data></node><node id="n406"><data key="mechanism">mechanism-d4-b0-d3-b1</data></node><node id="n385"><data key="mechanism">mechanism-d4-b0-d3-b1</data></node><node id="n897"><data key="mechanism">mechanism-d4-b0-d3-b1</data></node><node id="n72"><data key="mechanism">mechanism-d4-b0-d3-b1</data></node><node id="n587"><data key="mechanism">mechanism-d4-b0-d3-b1</data></node><node id="n588"><data key="mechanism">mechanism-d4-b0-d3-b1</data></node><node id="n549"><data key="mechanism">mechanism-d4-b0-d3-b1</data></node><node id="n518"><data key="mechanism">mechanism-d4-b0-d3-b1</data></node><node id="n698"><data key="mechanism">mechanism-d4-b0-d3-b1</data></node><node id="n802"><data key="mechanism">mechanism-d4-b0-d3-b1</data></node><node id="n708"><data key="mechanism">mechanism-d4-b0-d3-b1</data></node><node id="n983"><data key="mechanism">mechanism-d4-b0-d3-b1</data></node><node id="n941"><data key="mechanism">mechanism-d4-b0-d3-b1</data></node><node id="n942"><data key="mechanism">mechanism-d4-b0-d3-b1</data></node><node id="n905"><data key="mechanism">mechanism-d4-b0-d3-b1</data></node><node id="n378"><data key="mechanism">mechanism-d4-b0-d3-b1</data></node><node id="n733"><data key="mechanism">mechanism-d4-b0-d3-b1</data></node><node id="n532"><data key="mechanism">mechanism-d4-b0-d3-b1</data></node><node id="n938"><data key="mechanism">mechanism-d4-b0-d3-b1</data></node><node id="n102"><data key="mechanism">mechanism-d4-b0-d3-b1</data></node><node id="n638"><data key="mechanism">mechanism-d4-b0-d3-b1</data></node><node id="n1060"><data key="mechanism">mechanism-d4-b0-d3-b1</data></node><node id="n433"><data key="mechanism">mechanism-d4-b0-d3-b1</data></node><node id="n837"><data key="mechanism">mechanism-d4-b0-d3-b1</data></node><node id="n838"><data key="mechanism">mechanism-d4-b0-d3-b1</data></node><node id="n975"><data key="mechanism">mechanism-d4-b0-d3-b1</data></node><node id="n146"><data key="mechanism">mechanism-d4-b0-d3-b1</data></node><node id="n234"><data key="mechanism">mechanism-d4-b0-d3-b1</data></node><node id="n235"><data key="mechanism">mechanism-d4-b0-d3-b1</data></node><node id="n660"><data key="mechanism">mechanism-d4-b0-d3-b1</data></node><node id="n765"><data key="mechanism">mechanism-d4-b0-d3-b1</data></node><node id="n185"><data key="mechanism">mechanism-d4-b0-d3-b1</data></node><node id="n465"><data key="mechanism">mechanism-d4-b0-d3-b1</data></node><node id="n115"><data key="mechanism">mechanism-d4-b0-d3-b1</data></node><node id="n263"><data key="mechanism">mechanism-d4-b0-d3-b1</data></node><node id="n1030"><data key="mechanism">mechanism-d4-b0-d3-b1</data></node><node id="n563"><data key="mechanism">mechanism-d4-b0-d3-b1</data></node><node id="n161"><data key="mechanism">mechanism-d4-b0-d3-b1</data></node><node id="n828"><data key="mechanism">mechanism-d4-b0-d3-b1</data></node><node id="n525"><data key="mechanism">mechanism-d4-b0-d3-b1</data></node><node id="n861"><data key="mechanism">mechanism-d4-b0-d3-b1</data></node><node id="n963"><data key="mechanism">mechanism-d4-b0-d3-b1</data></node><node id="n328"><data key="mechanism">mechanism-d4-b0-d3-b1</data></node><node id="n822"><data key="mechanism">mechanism-d4-b0-d3-b1</data></node><node id="n199"><data key="mechanism">mechanism-d4-b0-d3-b1</data></node><node id="n926"><data key="mechanism">mechanism-d4-b0-d3-b1</data></node><edge id="0" source="n454" target="n938" label="dfc6ed08-4aa3-4b55-8758-8bb687d2622f"></edge><edge id="1" source="n912" target="n852" label="c1f64921-c00f-42d2-84bb-a1f61d848a3f"></edge><edge id="2" source="n298" target="n518" label="ab8b2cc4-54ff-49e3-8e6b-da5d7e5f97d7"></edge><edge id="3" source="n552" target="n861" label="80750c82-ae84-4005-8d7d-7ae1f0effaf7"></edge><edge id="4" source="n716" target="n549" label="4441ffb8-56f8-45ca-be80-d5092d6bef06"></edge><edge id="5" source="n751" target="n912" label="8949e8d9-1463-4ddf-b668-7145a0a016d5"></edge><edge id="6" source="n83" target="n378" label="2e4cefe2-167e-4242-a290-5e37bd64c502"></edge><edge id="7" source="n647" target="n72" label="eba81487-7cab-4494-9b76-6bd0dd148fab"></edge><edge id="8" source="n169" target="n552" label="4bf8925c-2525-4690-bb70-8585597139e6"></edge><edge id="9" source="n493" target="n563" label="eaf653ef-c5d6-4826-8c0a-4bcb96619940"></edge><edge id="10" source="n406" target="n828" label="0a513b52-d45b-4e33-958c-1ed3795cf6b4"></edge><edge id="11" source="n385" target="n660" label="a7d22825-a880-488e-95ec-684de64a066c"></edge><edge id="12" source="n897" target="n465" label="c214fec4-9490-4262-b1e8-97160cf1ec2e"></edge><edge id="13" source="n72" target="n1013" label="a7646b8c-4f39-4d21-86b6-2a65caac3284"></edge><edge id="14" source="n587" target="n983" label="c3ec01db-994a-47d6-b319-31b64bf9968a"></edge><edge id="24" source="n588" target="n698" label="f8651832-132f-4cc1-8ec1-a9d0ba80e5e7"></edge><edge id="15" source="n588" target="n587" label="4b1b6569-2987-4c01-8322-337424dcfb3d"></edge><edge id="25" source="n588" target="n493" label="115b8994-8d0b-476f-b8a2-af76af2a43c5"></edge><edge id="27" source="n588" target="n942" label="b0a3932f-c597-4e90-b4fc-2e8816273b3e"></edge><edge id="21" source="n588" target="n837" label="cbdabc1f-0eb0-4c11-9109-402a54735bba"></edge><edge id="20" source="n588" target="n406" label="1e13327e-21c2-4654-ad38-5614f280af62"></edge><edge id="22" source="n588" target="n115" label="96c28c0c-6343-4037-a151-10320e02dfba"></edge><edge id="29" source="n588" target="n169" label="fcd0571c-1dd0-4a42-97d2-2e86bc5da94b"></edge><edge id="16" source="n588" target="n1060" label="8f09658e-19f5-4acb-a15c-126c0351768f"></edge><edge id="19" source="n588" target="n525" label="3c3d2a52-f0eb-44e0-8eae-13b82da7b2a1"></edge><edge id="23" source="n588" target="n235" label="2b01ed20-d3c9-4fcb-ad19-5e64febaa994"></edge><edge id="28" source="n588" target="n146" label="f9c2ce24-f176-4b2e-9502-3eb7ecdec836"></edge><edge id="17" source="n588" target="n822" label="699902e2-d210-420e-9f34-ac993b26df0d"></edge><edge id="18" source="n588" target="n161" label="535c9885-566f-4935-aba8-4ea350affacc"></edge><edge id="26" source="n588" target="n975" label="592df5c9-26fd-4301-903e-9a99ee5e2c65"></edge><edge id="30" source="n549" target="n642" label="8a6280be-ec1a-4592-8162-23e5e0e47528"></edge><edge id="31" source="n698" target="n802" label="7de8757a-7e23-46cb-8eee-b5b15db4f93b"></edge><edge id="32" source="n802" target="n185" label="39727abc-014f-4f79-95c2-a244a98f371c"></edge><edge id="33" source="n708" target="n733" label="ba5378b2-401d-4016-ae7f-e018f4bccbf8"></edge><edge id="34" source="n983" target="n199" label="a677c202-f439-46c8-8d36-1734e2b08753"></edge><edge id="35" source="n941" target="n234" label="178214e0-68b4-4c31-af19-ad4e2b4d060d"></edge><edge id="36" source="n942" target="n263" label="aca57f52-2618-45ed-876c-f0d91e774c76"></edge><edge id="37" source="n905" target="n897" label="7807dfb2-2cb5-41d0-87f1-cda30dbf3d70"></edge><edge id="38" source="n733" target="n102" label="11b1addf-2915-4d5c-a492-a4d798aa1951"></edge><edge id="39" source="n532" target="n1030" label="bfd462c5-1ffb-4f67-b6a2-09fb144621f6"></edge><edge id="40" source="n938" target="n318" label="03c0658f-1698-499d-a098-e0449a700abf"></edge><edge id="41" source="n1060" target="n716" label="bac22bcf-277e-4049-b3e4-737d97cf0d26"></edge><edge id="42" source="n433" target="n83" label="0d3e7d7a-cf17-4c13-9386-28885e2b37b5"></edge><edge id="43" source="n837" target="n751" label="0f3f8f81-baaa-470c-abbe-933096a6dbea"></edge><edge id="44" source="n838" target="n963" label="e818097e-e1b9-4a8f-9fbb-afe2614a9a7f"></edge><edge id="45" source="n975" target="n708" label="9e701056-2260-4523-90cb-3013be15a63e"></edge><edge id="46" source="n146" target="n454" label="bbb0cd43-21a2-444b-83f9-b969ca92b68d"></edge><edge id="47" source="n234" target="n765" label="b33bcce3-0268-4662-b629-50a4e9aa8292"></edge><edge id="48" source="n235" target="n905" label="33b384e4-5211-42cb-b76f-49960e53ddbd"></edge><edge id="49" source="n185" target="n998" label="ed7b9104-d225-4474-ba9b-f9ade3ba0172"></edge><edge id="50" source="n115" target="n647" label="79edd3e4-16ca-448e-95b3-4df43fdb9c01"></edge><edge id="51" source="n263" target="n532" label="ed7f14ad-d6d4-4f03-9342-c646af19a534"></edge><edge id="52" source="n563" target="n838" label="1c8ce937-f844-4556-894b-68cc042e850f"></edge><edge id="53" source="n161" target="n328" label="9a4bb811-1188-40a6-aedd-3fa6a6e70ba3"></edge><edge id="54" source="n828" target="n385" label="57aed6bf-d5d2-41a7-8e8a-b92531e35a36"></edge><edge id="55" source="n525" target="n941" label="718f0ba4-81b7-4f53-90cc-1e6dc89b7420"></edge><edge id="56" source="n861" target="n638" label="6851e912-4e41-4a84-b14d-6fadffc53d71"></edge><edge id="57" source="n328" target="n298" label="4f2b0645-37df-4248-a290-0a2b27b1e7a1"></edge><edge id="58" source="n822" target="n433" label="7d2c07e2-b0c7-448c-82f0-2f1e8ca57764"></edge><edge id="59" source="n199" target="n926" label="cdd6dec7-8f6c-4475-92e4-ccf09b5cbd39"></edge></graph></graphml>