<?xml version="1.0" ?><graphml xmlns="http://graphml.graphdrawing.org/xmlns" xmlns:xsi="http://www.w3.org/2001/XMLSchema-instance" xsi:schemaLocation="http://graphml.graphdrawing.org/xmlns http://graphml.graphdrawing.org/xmlns/1.1/graphml.xsd"><key id="mechanism" for="node" attr.name="mechanism" attr.type="string"></key><graph id="G" edgedefault="directed"><node id="n724"><data key="mechanism">mechanism-d4-b0-d3-b1-d2-b0-d1-b0</data></node><node id="n835"><data key="mechanism">mechanism-d4-b0-d3-b1-d2-b0-d1-b0-d0-b0</data></node><node id="n327"><data key="mechanism">mechanism-d4-b1-d3-b1-d2-b0-d1-b0</data></node><node id="n282"><data key="mechanism">mechanism-d4-b0-d3-b1</data></node><node id="n755"><data key="mechanism">mechanism-d4-b0-d3-b1-d2-b0-d1-b0-d0-b0</data></node><node id="n381"><data key="mechanism">mechanism-d4-b2-d3-b1-d2-b0</data></node><node id="n842"><data key="mechanism">mechanism-d4-b1-d3-b1-d2-b0-d1-b0</data></node><node id="n39"><data key="mechanism">mechanism-d4-b2-d3-b1-d2-b0</data></node><node id="n972"><data key="mechanism">mechanism-d4-b2-d3-b1-d2-b0-d1-b0</data></node><node id="n859"><data key="mechanism">mechanism-d4-b0-d3-b1-d2-b0</data></node><edge id="0" source="n724" target="n381" label="c237245d-fb9a-4ec9-8d94-b74297338f34"></edge><edge id="1" source="n282" target="n859" label="9b78c525-be9e-481b-b624-811d3d345e45"></edge><edge id="6" source="n39" target="n282" label="8ed88899-748c-43f6-8b73-79eabbfa068c"></edge><edge id="4" source="n39" target="n724" label="4bb5d978-2260-4305-bc0e-9d61ac813f2e"></edge><edge id="3" source="n39" target="n835" label="eb205da4-1baf-43e6-a723-c567abe294aa"></edge><edge id="5" source="n39" target="n327" label="05f6ed50-5dc8-49fb-adaa-e537b26c73da"></edge><edge id="7" source="n39" target="n842" label="48cd3a34-1eed-4445-9b70-7f5074c86653"></edge><edge id="2" source="n39" target="n972" label="5f6dbbfe-1727-4fc5-b19d-d117946693c8"></edge><edge id="8" source="n972" target="n755" label="b7cce333-bdd4-4e8d-be4f-912b80a1a562"></edge></graph></graphml>