<?xml version="1.0" ?><graphml xmlns="http://graphml.graphdrawing.org/xmlns" xmlns:xsi="http://www.w3.org/2001/XMLSchema-instance" xsi:schemaLocation="http://graphml.graphdrawing.org/xmlns http://graphml.graphdrawing.org/xmlns/1.1/graphml.xsd"><key id="mechanism" for="node" attr.name="mechanism" attr.type="string"></key><graph id="G" edgedefault="directed"><node id="n366"><data key="mechanism">mechanism-d4-b0-d3-b1</data></node><node id="n445"><data key="mechanism">mechanism-d4-b0-d3-b1-d2-b0-d1-b0-d0-b0</data></node><node id="n649"><data key="mechanism">mechanism-d4-b0-d3-b1-d2-b0</data></node><node id="n810"><data key="mechanism">mechanism-d4-b0-d3-b1-d2-b0</data></node><node id="n428"><data key="mechanism">mechanism-d4-b0-d3-b1-d2-b0-d1-b0-d0-b0</data></node><node id="n703"><data key="mechanism">mechanism-d4-b0-d3-b1-d2-b0-d1-b0-d0-b0</data></node><node id="n342"><data key="mechanism">mechanism-d4-b0-d3-b1-d2-b0-d1-b0</data></node><node id="n246"><data key="mechanism">mechanism-d4-b0-d3-b1-d2-b0-d1-b0-d0-b0</data></node><node id="n39"><data key="mechanism">mechanism-d4-b0-d3-b1-d2-b0-d1-b0-d0-b0</data></node><node id="n217"><data key="mechanism">mechanism-d4-b0-d3-b1-d2-b0-d1-b0-d0-b0</data></node><node id="n251"><data key="mechanism">mechanism-d4-b0-d3-b1-d2-b0-d1-b0-d0-b0</data></node><edge id="0" source="n445" target="n342" label="a778abfb-6237-4130-a01a-0b37f69dcdba"></edge><edge id="1" source="n649" target="n39" label="557e2702-c6e4-480c-92ad-3f29468b463d"></edge><edge id="2" source="n428" target="n217" label="625cc5ce-cae3-4967-9e21-dc6e611c3b22"></edge><edge id="7" source="n703" target="n810" label="e638e4cf-5985-402b-bede-0696cc96eccb"></edge><edge id="3" source="n703" target="n445" label="46babdc5-f164-4bc2-a3a4-7e94dbb56f0f"></edge><edge id="5" source="n703" target="n251" label="a7e125dd-3e34-4402-8ff1-ff7388ee8837"></edge><edge id="4" source="n703" target="n649" label="e2a573e8-075e-4155-bb50-f435a2fb7419"></edge><edge id="9" source="n703" target="n428" label="073e3c6e-af93-4091-a2f6-69ade2749653"></edge><edge id="6" source="n703" target="n246" label="08d9cfe6-7a24-4e2e-8283-a7c794065a76"></edge><edge id="8" source="n703" target="n366" label="a0b85c9b-956f-4303-aad5-cb3e125abfd9"></edge></graph></graphml>