<?xml version="1.0" encoding="UTF-8"?>
<allEvidences>
   <evidences path="0">
      <evidence>
         <mechanism>encryption-message-in-transit</mechanism>
         <state>n0</state>
         <inputs>
            <input>
               <key>host</key>
               <value></value>
               <domain>d1</domain>
            </input>
         </inputs>
         <expectedOutput>
            <output>
               <key>Result</key>
               <value>true</value>
               <domain>d1</domain>
            </output>
         </expectedOutput>
      </evidence>
      <evidence>
         <mechanism>encryption-internal-communications</mechanism>
         <state>n1</state>
         <inputs>
            <input>
               <key>serviceUri</key>
               <value></value>
               <domain>d1</domain>
            </input>
         </inputs>
         <expectedOutput>
            <output>
               <key>Result</key>
               <value>true</value>
               <domain>d1</domain>
            </output>
         </expectedOutput>
      </evidence>
      <evidence>
         <mechanism>encryption-data-at-rest</mechanism>
         <state>n2</state>
         <inputs>
            <input>
               <key>local</key>
               <value></value>
               <domain>d1</domain>
            </input>
         </inputs>
         <expectedOutput>
            <output>
               <key>Result</key>
               <value>true</value>
               <domain>d1</domain>
            </output>
         </expectedOutput>
      </evidence>
   </evidences>
</allEvidences>