<?xml version="1.0" ?><graphml xmlns="http://graphml.graphdrawing.org/xmlns" xmlns:xsi="http://www.w3.org/2001/XMLSchema-instance" xsi:schemaLocation="http://graphml.graphdrawing.org/xmlns http://graphml.graphdrawing.org/xmlns/1.1/graphml.xsd"><key id="mechanism" for="node" attr.name="mechanism" attr.type="string"></key><graph id="G" edgedefault="directed"><node id="n261"><data key="mechanism">mechanism-d4-b1-d3-b1-d2-b0-d1-b0-d0-b0</data></node><node id="n492"><data key="mechanism">mechanism-d4-b2-d3-b1-d2-b0</data></node><node id="n981"><data key="mechanism">mechanism-d4-b2-d3-b1-d2-b0-d1-b0</data></node><node id="n1003"><data key="mechanism">mechanism-d4-b2-d3-b1-d2-b0-d1-b0</data></node><node id="n177"><data key="mechanism">mechanism-d4-b2-d3-b1-d2-b0</data></node><node id="n380"><data key="mechanism">mechanism-d4-b0-d3-b1-d2-b0</data></node><node id="n500"><data key="mechanism">mechanism-d4-b0-d3-b1-d2-b0</data></node><node id="n922"><data key="mechanism">mechanism-d4-b1-d3-b1-d2-b0-d1-b0-d0-b0</data></node><node id="n635"><data key="mechanism">mechanism-d4-b2-d3-b1-d2-b0</data></node><node id="n924"><data key="mechanism">mechanism-d4-b2-d3-b1-d2-b0-d1-b0-d0-b0</data></node><node id="n15"><data key="mechanism">mechanism-d4-b0-d3-b1-d2-b0-d1-b0-d0-b0</data></node><edge id="0" source="n261" target="n635" label="865dcb7f-148c-4142-868f-ef4511d4ef59"></edge><edge id="1" source="n492" target="n922" label="0cbf4f13-0d52-488e-8db9-bdec78244c5c"></edge><edge id="2" source="n177" target="n1003" label="d5faf559-c517-406f-a000-9efaf70587c2"></edge><edge id="3" source="n500" target="n981" label="d2655e98-6c49-4e1d-a67c-7beddd3a4432"></edge><edge id="9" source="n15" target="n177" label="d516513b-2519-46fa-95c7-b35dfdc9037d"></edge><edge id="6" source="n15" target="n380" label="2490ef71-bdfe-48d5-bdf4-4c7407bfd47b"></edge><edge id="8" source="n15" target="n492" label="4e8f27d6-4c58-4caf-975c-696725ce720a"></edge><edge id="5" source="n15" target="n924" label="9d14db75-0735-4285-8a3f-d47439978833"></edge><edge id="7" source="n15" target="n500" label="82d17235-fa85-4f15-94a4-9a9fe21bb814"></edge><edge id="4" source="n15" target="n261" label="4c57b822-c16b-44b9-b8a4-89a4286f90ef"></edge></graph></graphml>